[
    {
        "team": "Cleveland Guardians"
    },
    {
        "MatchNumber": 15,
        "RoundNumber": 1,
        "DateUtc": "2023-03-31 02:10:00Z",
        "Location": "T-Mobile Park",
        "HomeTeam": "Seattle Mariners",
        "AwayTeam": "Cleveland Guardians",
        "Group": null,
        "HomeTeamScore": 3,
        "AwayTeamScore": 0
    },
    {
        "MatchNumber": 20,
        "RoundNumber": 1,
        "DateUtc": "2023-04-01 02:10:00Z",
        "Location": "T-Mobile Park",
        "HomeTeam": "Seattle Mariners",
        "AwayTeam": "Cleveland Guardians",
        "Group": null,
        "HomeTeamScore": 4,
        "AwayTeamScore": 9
    },
    {
        "MatchNumber": 35,
        "RoundNumber": 1,
        "DateUtc": "2023-04-02 01:40:00Z",
        "Location": "T-Mobile Park",
        "HomeTeam": "Seattle Mariners",
        "AwayTeam": "Cleveland Guardians",
        "Group": null,
        "HomeTeamScore": 0,
        "AwayTeamScore": 2
    },
    {
        "MatchNumber": 49,
        "RoundNumber": 1,
        "DateUtc": "2023-04-02 20:10:00Z",
        "Location": "T-Mobile Park",
        "HomeTeam": "Seattle Mariners",
        "AwayTeam": "Cleveland Guardians",
        "Group": null,
        "HomeTeamScore": 5,
        "AwayTeamScore": 6
    },
    {
        "MatchNumber": 62,
        "RoundNumber": 1,
        "DateUtc": "2023-04-04 01:40:00Z",
        "Location": "Oakland Coliseum",
        "HomeTeam": "Oakland Athletics",
        "AwayTeam": "Cleveland Guardians",
        "Group": null,
        "HomeTeamScore": 11,
        "AwayTeamScore": 12
    },
    {
        "MatchNumber": 77,
        "RoundNumber": 1,
        "DateUtc": "2023-04-05 01:40:00Z",
        "Location": "Oakland Coliseum",
        "HomeTeam": "Oakland Athletics",
        "AwayTeam": "Cleveland Guardians",
        "Group": null,
        "HomeTeamScore": 4,
        "AwayTeamScore": 3
    },
    {
        "MatchNumber": 89,
        "RoundNumber": 2,
        "DateUtc": "2023-04-05 19:37:00Z",
        "Location": "Oakland Coliseum",
        "HomeTeam": "Oakland Athletics",
        "AwayTeam": "Cleveland Guardians",
        "Group": null,
        "HomeTeamScore": 4,
        "AwayTeamScore": 6
    },
    {
        "MatchNumber": 104,
        "RoundNumber": 2,
        "DateUtc": "2023-04-07 20:10:00Z",
        "Location": "Progressive Field",
        "HomeTeam": "Cleveland Guardians",
        "AwayTeam": "Seattle Mariners",
        "Group": null,
        "HomeTeamScore": 3,
        "AwayTeamScore": 5
    },
    {
        "MatchNumber": 120,
        "RoundNumber": 2,
        "DateUtc": "2023-04-08 22:10:00Z",
        "Location": "Progressive Field",
        "HomeTeam": "Cleveland Guardians",
        "AwayTeam": "Seattle Mariners",
        "Group": null,
        "HomeTeamScore": 2,
        "AwayTeamScore": 3
    },
    {
        "MatchNumber": 133,
        "RoundNumber": 2,
        "DateUtc": "2023-04-09 17:40:00Z",
        "Location": "Progressive Field",
        "HomeTeam": "Cleveland Guardians",
        "AwayTeam": "Seattle Mariners",
        "Group": null,
        "HomeTeamScore": 7,
        "AwayTeamScore": 6
    },
    {
        "MatchNumber": 144,
        "RoundNumber": 2,
        "DateUtc": "2023-04-10 22:10:00Z",
        "Location": "Progressive Field",
        "HomeTeam": "Cleveland Guardians",
        "AwayTeam": "New York Yankees",
        "Group": null,
        "HomeTeamScore": 3,
        "AwayTeamScore": 2
    },
    {
        "MatchNumber": 157,
        "RoundNumber": 2,
        "DateUtc": "2023-04-11 22:10:00Z",
        "Location": "Progressive Field",
        "HomeTeam": "Cleveland Guardians",
        "AwayTeam": "New York Yankees",
        "Group": null,
        "HomeTeamScore": 2,
        "AwayTeamScore": 11
    },
    {
        "MatchNumber": 175,
        "RoundNumber": 3,
        "DateUtc": "2023-04-12 17:10:00Z",
        "Location": "Progressive Field",
        "HomeTeam": "Cleveland Guardians",
        "AwayTeam": "New York Yankees",
        "Group": null,
        "HomeTeamScore": 3,
        "AwayTeamScore": 4
    },
    {
        "MatchNumber": 197,
        "RoundNumber": 3,
        "DateUtc": "2023-04-14 23:05:00Z",
        "Location": "Nationals Park",
        "HomeTeam": "Washington Nationals",
        "AwayTeam": "Cleveland Guardians",
        "Group": null,
        "HomeTeamScore": 3,
        "AwayTeamScore": 4
    },
    {
        "MatchNumber": 214,
        "RoundNumber": 3,
        "DateUtc": "2023-04-15 20:05:00Z",
        "Location": "Nationals Park",
        "HomeTeam": "Washington Nationals",
        "AwayTeam": "Cleveland Guardians",
        "Group": null,
        "HomeTeamScore": 4,
        "AwayTeamScore": 6
    },
    {
        "MatchNumber": 226,
        "RoundNumber": 3,
        "DateUtc": "2023-04-16 17:35:00Z",
        "Location": "Nationals Park",
        "HomeTeam": "Washington Nationals",
        "AwayTeam": "Cleveland Guardians",
        "Group": null,
        "HomeTeamScore": 7,
        "AwayTeamScore": 6
    },
    {
        "MatchNumber": 252,
        "RoundNumber": 3,
        "DateUtc": "2023-04-18 17:10:00Z",
        "Location": "Comerica Park",
        "HomeTeam": "Detroit Tigers",
        "AwayTeam": "Cleveland Guardians",
        "Group": null,
        "HomeTeamScore": 1,
        "AwayTeamScore": 0
    },
    {
        "MatchNumber": 240,
        "RoundNumber": 3,
        "DateUtc": "2023-04-18 17:15:00Z",
        "Location": "Comerica Park",
        "HomeTeam": "Detroit Tigers",
        "AwayTeam": "Cleveland Guardians",
        "Group": null,
        "HomeTeamScore": 4,
        "AwayTeamScore": 3
    },
    {
        "MatchNumber": 268,
        "RoundNumber": 4,
        "DateUtc": "2023-04-19 17:10:00Z",
        "Location": "Comerica Park",
        "HomeTeam": "Detroit Tigers",
        "AwayTeam": "Cleveland Guardians",
        "Group": null,
        "HomeTeamScore": 2,
        "AwayTeamScore": 3
    },
    {
        "MatchNumber": 310,
        "RoundNumber": 4,
        "DateUtc": "2023-04-22 19:10:00Z",
        "Location": "Progressive Field",
        "HomeTeam": "Cleveland Guardians",
        "AwayTeam": "Miami Marlins",
        "Group": null,
        "HomeTeamScore": 1,
        "AwayTeamScore": 6
    },
    {
        "MatchNumber": 295,
        "RoundNumber": 4,
        "DateUtc": "2023-04-22 19:15:00Z",
        "Location": "Progressive Field",
        "HomeTeam": "Cleveland Guardians",
        "AwayTeam": "Miami Marlins",
        "Group": null,
        "HomeTeamScore": 1,
        "AwayTeamScore": 6
    },
    {
        "MatchNumber": 325,
        "RoundNumber": 4,
        "DateUtc": "2023-04-23 17:40:00Z",
        "Location": "Progressive Field",
        "HomeTeam": "Cleveland Guardians",
        "AwayTeam": "Miami Marlins",
        "Group": null,
        "HomeTeamScore": 7,
        "AwayTeamScore": 4
    },
    {
        "MatchNumber": 334,
        "RoundNumber": 4,
        "DateUtc": "2023-04-24 22:10:00Z",
        "Location": "Progressive Field",
        "HomeTeam": "Cleveland Guardians",
        "AwayTeam": "Colorado Rockies",
        "Group": null,
        "HomeTeamScore": 0,
        "AwayTeamScore": 6
    },
    {
        "MatchNumber": 345,
        "RoundNumber": 4,
        "DateUtc": "2023-04-25 22:10:00Z",
        "Location": "Progressive Field",
        "HomeTeam": "Cleveland Guardians",
        "AwayTeam": "Colorado Rockies",
        "Group": null,
        "HomeTeamScore": 1,
        "AwayTeamScore": 5
    },
    {
        "MatchNumber": 363,
        "RoundNumber": 5,
        "DateUtc": "2023-04-26 17:10:00Z",
        "Location": "Progressive Field",
        "HomeTeam": "Cleveland Guardians",
        "AwayTeam": "Colorado Rockies",
        "Group": null,
        "HomeTeamScore": 4,
        "AwayTeamScore": 1
    },
    {
        "MatchNumber": 391,
        "RoundNumber": 5,
        "DateUtc": "2023-04-28 23:10:00Z",
        "Location": "Fenway Park",
        "HomeTeam": "Boston Red Sox",
        "AwayTeam": "Cleveland Guardians",
        "Group": null,
        "HomeTeamScore": 2,
        "AwayTeamScore": 5
    },
    {
        "MatchNumber": 407,
        "RoundNumber": 5,
        "DateUtc": "2023-04-29 20:10:00Z",
        "Location": "Fenway Park",
        "HomeTeam": "Boston Red Sox",
        "AwayTeam": "Cleveland Guardians",
        "Group": null,
        "HomeTeamScore": 8,
        "AwayTeamScore": 7
    },
    {
        "MatchNumber": 416,
        "RoundNumber": 5,
        "DateUtc": "2023-04-30 17:35:00Z",
        "Location": "Fenway Park",
        "HomeTeam": "Boston Red Sox",
        "AwayTeam": "Cleveland Guardians",
        "Group": null,
        "HomeTeamScore": 7,
        "AwayTeamScore": 1
    },
    {
        "MatchNumber": 432,
        "RoundNumber": 5,
        "DateUtc": "2023-05-01 23:05:00Z",
        "Location": "Yankee Stadium",
        "HomeTeam": "New York Yankees",
        "AwayTeam": "Cleveland Guardians",
        "Group": null,
        "HomeTeamScore": 2,
        "AwayTeamScore": 3
    },
    {
        "MatchNumber": 441,
        "RoundNumber": 5,
        "DateUtc": "2023-05-02 23:05:00Z",
        "Location": "Yankee Stadium",
        "HomeTeam": "New York Yankees",
        "AwayTeam": "Cleveland Guardians",
        "Group": null,
        "HomeTeamScore": 4,
        "AwayTeamScore": 2
    },
    {
        "MatchNumber": 460,
        "RoundNumber": 6,
        "DateUtc": "2023-05-03 23:05:00Z",
        "Location": "Yankee Stadium",
        "HomeTeam": "New York Yankees",
        "AwayTeam": "Cleveland Guardians",
        "Group": null,
        "HomeTeamScore": 4,
        "AwayTeamScore": 3
    },
    {
        "MatchNumber": 483,
        "RoundNumber": 6,
        "DateUtc": "2023-05-05 23:10:00Z",
        "Location": "Progressive Field",
        "HomeTeam": "Cleveland Guardians",
        "AwayTeam": "Minnesota Twins",
        "Group": null,
        "HomeTeamScore": 0,
        "AwayTeamScore": 2
    },
    {
        "MatchNumber": 496,
        "RoundNumber": 6,
        "DateUtc": "2023-05-06 22:10:00Z",
        "Location": "Progressive Field",
        "HomeTeam": "Cleveland Guardians",
        "AwayTeam": "Minnesota Twins",
        "Group": null,
        "HomeTeamScore": 4,
        "AwayTeamScore": 3
    },
    {
        "MatchNumber": 511,
        "RoundNumber": 6,
        "DateUtc": "2023-05-07 17:40:00Z",
        "Location": "Progressive Field",
        "HomeTeam": "Cleveland Guardians",
        "AwayTeam": "Minnesota Twins",
        "Group": null,
        "HomeTeamScore": 2,
        "AwayTeamScore": 0
    },
    {
        "MatchNumber": 522,
        "RoundNumber": 6,
        "DateUtc": "2023-05-08 22:10:00Z",
        "Location": "Progressive Field",
        "HomeTeam": "Cleveland Guardians",
        "AwayTeam": "Detroit Tigers",
        "Group": null,
        "HomeTeamScore": 2,
        "AwayTeamScore": 6
    },
    {
        "MatchNumber": 533,
        "RoundNumber": 6,
        "DateUtc": "2023-05-09 22:10:00Z",
        "Location": "Progressive Field",
        "HomeTeam": "Cleveland Guardians",
        "AwayTeam": "Detroit Tigers",
        "Group": null,
        "HomeTeamScore": 2,
        "AwayTeamScore": 0
    },
    {
        "MatchNumber": 550,
        "RoundNumber": 7,
        "DateUtc": "2023-05-10 17:10:00Z",
        "Location": "Progressive Field",
        "HomeTeam": "Cleveland Guardians",
        "AwayTeam": "Detroit Tigers",
        "Group": null,
        "HomeTeamScore": 0,
        "AwayTeamScore": 5
    },
    {
        "MatchNumber": 575,
        "RoundNumber": 7,
        "DateUtc": "2023-05-12 23:10:00Z",
        "Location": "Progressive Field",
        "HomeTeam": "Cleveland Guardians",
        "AwayTeam": "Los Angeles Angels",
        "Group": null,
        "HomeTeamScore": 4,
        "AwayTeamScore": 5
    },
    {
        "MatchNumber": 592,
        "RoundNumber": 7,
        "DateUtc": "2023-05-13 22:10:00Z",
        "Location": "Progressive Field",
        "HomeTeam": "Cleveland Guardians",
        "AwayTeam": "Los Angeles Angels",
        "Group": null,
        "HomeTeamScore": 8,
        "AwayTeamScore": 6
    },
    {
        "MatchNumber": 599,
        "RoundNumber": 7,
        "DateUtc": "2023-05-14 15:35:00Z",
        "Location": "Progressive Field",
        "HomeTeam": "Cleveland Guardians",
        "AwayTeam": "Los Angeles Angels",
        "Group": null,
        "HomeTeamScore": 4,
        "AwayTeamScore": 3
    },
    {
        "MatchNumber": 635,
        "RoundNumber": 7,
        "DateUtc": "2023-05-17 00:10:00Z",
        "Location": "Guaranteed Rate Field",
        "HomeTeam": "Chicago White Sox",
        "AwayTeam": "Cleveland Guardians",
        "Group": null,
        "HomeTeamScore": 8,
        "AwayTeamScore": 3
    },
    {
        "MatchNumber": 655,
        "RoundNumber": 8,
        "DateUtc": "2023-05-18 00:10:00Z",
        "Location": "Guaranteed Rate Field",
        "HomeTeam": "Chicago White Sox",
        "AwayTeam": "Cleveland Guardians",
        "Group": null,
        "HomeTeamScore": 7,
        "AwayTeamScore": 2
    },
    {
        "MatchNumber": 659,
        "RoundNumber": 8,
        "DateUtc": "2023-05-18 18:10:00Z",
        "Location": "Guaranteed Rate Field",
        "HomeTeam": "Chicago White Sox",
        "AwayTeam": "Cleveland Guardians",
        "Group": null,
        "HomeTeamScore": 1,
        "AwayTeamScore": 3
    },
    {
        "MatchNumber": 668,
        "RoundNumber": 8,
        "DateUtc": "2023-05-19 23:10:00Z",
        "Location": "Citi Field",
        "HomeTeam": "New York Mets",
        "AwayTeam": "Cleveland Guardians",
        "Group": null,
        "HomeTeamScore": 10,
        "AwayTeamScore": 9
    },
    {
        "MatchNumber": 684,
        "RoundNumber": 8,
        "DateUtc": "2023-05-21 17:40:00Z",
        "Location": "Citi Field",
        "HomeTeam": "New York Mets",
        "AwayTeam": "Cleveland Guardians",
        "Group": null,
        "HomeTeamScore": 5,
        "AwayTeamScore": 4
    },
    {
        "MatchNumber": 706,
        "RoundNumber": 8,
        "DateUtc": "2023-05-21 23:10:00Z",
        "Location": "Citi Field",
        "HomeTeam": "New York Mets",
        "AwayTeam": "Cleveland Guardians",
        "Group": null,
        "HomeTeamScore": 2,
        "AwayTeamScore": 1
    },
    {
        "MatchNumber": 707,
        "RoundNumber": 8,
        "DateUtc": "2023-05-22 22:10:00Z",
        "Location": "Progressive Field",
        "HomeTeam": "Cleveland Guardians",
        "AwayTeam": "Chicago White Sox",
        "Group": null,
        "HomeTeamScore": 3,
        "AwayTeamScore": 0
    },
    {
        "MatchNumber": 719,
        "RoundNumber": 8,
        "DateUtc": "2023-05-23 22:10:00Z",
        "Location": "Progressive Field",
        "HomeTeam": "Cleveland Guardians",
        "AwayTeam": "Chicago White Sox",
        "Group": null,
        "HomeTeamScore": 2,
        "AwayTeamScore": 4
    },
    {
        "MatchNumber": 737,
        "RoundNumber": 9,
        "DateUtc": "2023-05-24 17:10:00Z",
        "Location": "Progressive Field",
        "HomeTeam": "Cleveland Guardians",
        "AwayTeam": "Chicago White Sox",
        "Group": null,
        "HomeTeamScore": 0,
        "AwayTeamScore": 6
    },
    {
        "MatchNumber": 764,
        "RoundNumber": 9,
        "DateUtc": "2023-05-26 23:10:00Z",
        "Location": "Progressive Field",
        "HomeTeam": "Cleveland Guardians",
        "AwayTeam": "St. Louis Cardinals",
        "Group": null,
        "HomeTeamScore": 4,
        "AwayTeamScore": 3
    },
    {
        "MatchNumber": 786,
        "RoundNumber": 9,
        "DateUtc": "2023-05-27 23:15:00Z",
        "Location": "Progressive Field",
        "HomeTeam": "Cleveland Guardians",
        "AwayTeam": "St. Louis Cardinals",
        "Group": null,
        "HomeTeamScore": 1,
        "AwayTeamScore": 2
    },
    {
        "MatchNumber": 792,
        "RoundNumber": 9,
        "DateUtc": "2023-05-28 17:40:00Z",
        "Location": "Progressive Field",
        "HomeTeam": "Cleveland Guardians",
        "AwayTeam": "St. Louis Cardinals",
        "Group": null,
        "HomeTeamScore": 4,
        "AwayTeamScore": 3
    },
    {
        "MatchNumber": 804,
        "RoundNumber": 9,
        "DateUtc": "2023-05-29 17:05:00Z",
        "Location": "Oriole Park at Camden Yards",
        "HomeTeam": "Baltimore Orioles",
        "AwayTeam": "Cleveland Guardians",
        "Group": null,
        "HomeTeamScore": 0,
        "AwayTeamScore": 5
    },
    {
        "MatchNumber": 817,
        "RoundNumber": 9,
        "DateUtc": "2023-05-30 23:05:00Z",
        "Location": "Oriole Park at Camden Yards",
        "HomeTeam": "Baltimore Orioles",
        "AwayTeam": "Cleveland Guardians",
        "Group": null,
        "HomeTeamScore": 8,
        "AwayTeamScore": 5
    },
    {
        "MatchNumber": 833,
        "RoundNumber": 10,
        "DateUtc": "2023-05-31 19:05:00Z",
        "Location": "Oriole Park at Camden Yards",
        "HomeTeam": "Baltimore Orioles",
        "AwayTeam": "Cleveland Guardians",
        "Group": null,
        "HomeTeamScore": 8,
        "AwayTeamScore": 12
    },
    {
        "MatchNumber": 849,
        "RoundNumber": 10,
        "DateUtc": "2023-06-01 23:40:00Z",
        "Location": "Target Field",
        "HomeTeam": "Minnesota Twins",
        "AwayTeam": "Cleveland Guardians",
        "Group": null,
        "HomeTeamScore": 7,
        "AwayTeamScore": 6
    },
    {
        "MatchNumber": 860,
        "RoundNumber": 10,
        "DateUtc": "2023-06-03 00:10:00Z",
        "Location": "Target Field",
        "HomeTeam": "Minnesota Twins",
        "AwayTeam": "Cleveland Guardians",
        "Group": null,
        "HomeTeamScore": 1,
        "AwayTeamScore": 0
    },
    {
        "MatchNumber": 877,
        "RoundNumber": 10,
        "DateUtc": "2023-06-03 23:15:00Z",
        "Location": "Target Field",
        "HomeTeam": "Minnesota Twins",
        "AwayTeam": "Cleveland Guardians",
        "Group": null,
        "HomeTeamScore": 2,
        "AwayTeamScore": 4
    },
    {
        "MatchNumber": 890,
        "RoundNumber": 10,
        "DateUtc": "2023-06-04 18:10:00Z",
        "Location": "Target Field",
        "HomeTeam": "Minnesota Twins",
        "AwayTeam": "Cleveland Guardians",
        "Group": null,
        "HomeTeamScore": 1,
        "AwayTeamScore": 2
    },
    {
        "MatchNumber": 911,
        "RoundNumber": 10,
        "DateUtc": "2023-06-06 23:10:00Z",
        "Location": "Progressive Field",
        "HomeTeam": "Cleveland Guardians",
        "AwayTeam": "Boston Red Sox",
        "Group": null,
        "HomeTeamScore": 4,
        "AwayTeamScore": 5
    },
    {
        "MatchNumber": 927,
        "RoundNumber": 11,
        "DateUtc": "2023-06-07 23:10:00Z",
        "Location": "Progressive Field",
        "HomeTeam": "Cleveland Guardians",
        "AwayTeam": "Boston Red Sox",
        "Group": null,
        "HomeTeamScore": 4,
        "AwayTeamScore": 2
    },
    {
        "MatchNumber": 941,
        "RoundNumber": 11,
        "DateUtc": "2023-06-08 23:10:00Z",
        "Location": "Progressive Field",
        "HomeTeam": "Cleveland Guardians",
        "AwayTeam": "Boston Red Sox",
        "Group": null,
        "HomeTeamScore": 10,
        "AwayTeamScore": 3
    },
    {
        "MatchNumber": 951,
        "RoundNumber": 11,
        "DateUtc": "2023-06-09 23:10:00Z",
        "Location": "Progressive Field",
        "HomeTeam": "Cleveland Guardians",
        "AwayTeam": "Houston Astros",
        "Group": null,
        "HomeTeamScore": 10,
        "AwayTeamScore": 9
    },
    {
        "MatchNumber": 970,
        "RoundNumber": 11,
        "DateUtc": "2023-06-10 22:10:00Z",
        "Location": "Progressive Field",
        "HomeTeam": "Cleveland Guardians",
        "AwayTeam": "Houston Astros",
        "Group": null,
        "HomeTeamScore": 4,
        "AwayTeamScore": 6
    },
    {
        "MatchNumber": 981,
        "RoundNumber": 11,
        "DateUtc": "2023-06-11 16:40:00Z",
        "Location": "Progressive Field",
        "HomeTeam": "Cleveland Guardians",
        "AwayTeam": "Houston Astros",
        "Group": null,
        "HomeTeamScore": 5,
        "AwayTeamScore": 0
    },
    {
        "MatchNumber": 1007,
        "RoundNumber": 11,
        "DateUtc": "2023-06-14 01:40:00Z",
        "Location": "Petco Park",
        "HomeTeam": "San Diego Padres",
        "AwayTeam": "Cleveland Guardians",
        "Group": null,
        "HomeTeamScore": 6,
        "AwayTeamScore": 3
    },
    {
        "MatchNumber": 1022,
        "RoundNumber": 12,
        "DateUtc": "2023-06-15 01:40:00Z",
        "Location": "Petco Park",
        "HomeTeam": "San Diego Padres",
        "AwayTeam": "Cleveland Guardians",
        "Group": null,
        "HomeTeamScore": 5,
        "AwayTeamScore": 0
    },
    {
        "MatchNumber": 1035,
        "RoundNumber": 12,
        "DateUtc": "2023-06-16 00:40:00Z",
        "Location": "Petco Park",
        "HomeTeam": "San Diego Padres",
        "AwayTeam": "Cleveland Guardians",
        "Group": null,
        "HomeTeamScore": 6,
        "AwayTeamScore": 8
    },
    {
        "MatchNumber": 1047,
        "RoundNumber": 12,
        "DateUtc": "2023-06-17 01:40:00Z",
        "Location": "Chase Field",
        "HomeTeam": "Arizona Diamondbacks",
        "AwayTeam": "Cleveland Guardians",
        "Group": null,
        "HomeTeamScore": 5,
        "AwayTeamScore": 1
    },
    {
        "MatchNumber": 1066,
        "RoundNumber": 12,
        "DateUtc": "2023-06-18 02:10:00Z",
        "Location": "Chase Field",
        "HomeTeam": "Arizona Diamondbacks",
        "AwayTeam": "Cleveland Guardians",
        "Group": null,
        "HomeTeamScore": 6,
        "AwayTeamScore": 3
    },
    {
        "MatchNumber": 1077,
        "RoundNumber": 12,
        "DateUtc": "2023-06-18 20:10:00Z",
        "Location": "Chase Field",
        "HomeTeam": "Arizona Diamondbacks",
        "AwayTeam": "Cleveland Guardians",
        "Group": null,
        "HomeTeamScore": 3,
        "AwayTeamScore": 12
    },
    {
        "MatchNumber": 1100,
        "RoundNumber": 12,
        "DateUtc": "2023-06-20 23:10:00Z",
        "Location": "Progressive Field",
        "HomeTeam": "Cleveland Guardians",
        "AwayTeam": "Oakland Athletics",
        "Group": null,
        "HomeTeamScore": 3,
        "AwayTeamScore": 2
    },
    {
        "MatchNumber": 1117,
        "RoundNumber": 13,
        "DateUtc": "2023-06-21 23:10:00Z",
        "Location": "Progressive Field",
        "HomeTeam": "Cleveland Guardians",
        "AwayTeam": "Oakland Athletics",
        "Group": null,
        "HomeTeamScore": 7,
        "AwayTeamScore": 6
    },
    {
        "MatchNumber": 1123,
        "RoundNumber": 13,
        "DateUtc": "2023-06-22 17:10:00Z",
        "Location": "Progressive Field",
        "HomeTeam": "Cleveland Guardians",
        "AwayTeam": "Oakland Athletics",
        "Group": null,
        "HomeTeamScore": 6,
        "AwayTeamScore": 1
    },
    {
        "MatchNumber": 1137,
        "RoundNumber": 13,
        "DateUtc": "2023-06-23 23:10:00Z",
        "Location": "Progressive Field",
        "HomeTeam": "Cleveland Guardians",
        "AwayTeam": "Milwaukee Brewers",
        "Group": null,
        "HomeTeamScore": 1,
        "AwayTeamScore": 7
    },
    {
        "MatchNumber": 1153,
        "RoundNumber": 13,
        "DateUtc": "2023-06-24 20:10:00Z",
        "Location": "Progressive Field",
        "HomeTeam": "Cleveland Guardians",
        "AwayTeam": "Milwaukee Brewers",
        "Group": null,
        "HomeTeamScore": 4,
        "AwayTeamScore": 2
    },
    {
        "MatchNumber": 1167,
        "RoundNumber": 13,
        "DateUtc": "2023-06-25 17:40:00Z",
        "Location": "Progressive Field",
        "HomeTeam": "Cleveland Guardians",
        "AwayTeam": "Milwaukee Brewers",
        "Group": null,
        "HomeTeamScore": 4,
        "AwayTeamScore": 5
    },
    {
        "MatchNumber": 1188,
        "RoundNumber": 13,
        "DateUtc": "2023-06-28 00:10:00Z",
        "Location": "Kauffman Stadium",
        "HomeTeam": "Kansas City Royals",
        "AwayTeam": "Cleveland Guardians",
        "Group": null,
        "HomeTeamScore": 1,
        "AwayTeamScore": 2
    },
    {
        "MatchNumber": 1204,
        "RoundNumber": 14,
        "DateUtc": "2023-06-29 00:10:00Z",
        "Location": "Kauffman Stadium",
        "HomeTeam": "Kansas City Royals",
        "AwayTeam": "Cleveland Guardians",
        "Group": null,
        "HomeTeamScore": 1,
        "AwayTeamScore": 14
    },
    {
        "MatchNumber": 1211,
        "RoundNumber": 14,
        "DateUtc": "2023-06-29 18:10:00Z",
        "Location": "Kauffman Stadium",
        "HomeTeam": "Kansas City Royals",
        "AwayTeam": "Cleveland Guardians",
        "Group": null,
        "HomeTeamScore": 4,
        "AwayTeamScore": 3
    },
    {
        "MatchNumber": 1221,
        "RoundNumber": 14,
        "DateUtc": "2023-06-30 18:20:00Z",
        "Location": "Wrigley Field",
        "HomeTeam": "Chicago Cubs",
        "AwayTeam": "Cleveland Guardians",
        "Group": null,
        "HomeTeamScore": 10,
        "AwayTeamScore": 1
    },
    {
        "MatchNumber": 1246,
        "RoundNumber": 14,
        "DateUtc": "2023-07-01 23:15:00Z",
        "Location": "Wrigley Field",
        "HomeTeam": "Chicago Cubs",
        "AwayTeam": "Cleveland Guardians",
        "Group": null,
        "HomeTeamScore": 0,
        "AwayTeamScore": 6
    },
    {
        "MatchNumber": 1260,
        "RoundNumber": 14,
        "DateUtc": "2023-07-02 21:05:00Z",
        "Location": "Wrigley Field",
        "HomeTeam": "Chicago Cubs",
        "AwayTeam": "Cleveland Guardians",
        "Group": null,
        "HomeTeamScore": 6,
        "AwayTeamScore": 8
    },
    {
        "MatchNumber": 1271,
        "RoundNumber": 14,
        "DateUtc": "2023-07-03 23:10:00Z",
        "Location": "Progressive Field",
        "HomeTeam": "Cleveland Guardians",
        "AwayTeam": "Atlanta Braves",
        "Group": null,
        "HomeTeamScore": 2,
        "AwayTeamScore": 4
    },
    {
        "MatchNumber": 1288,
        "RoundNumber": 14,
        "DateUtc": "2023-07-04 23:10:00Z",
        "Location": "Progressive Field",
        "HomeTeam": "Cleveland Guardians",
        "AwayTeam": "Atlanta Braves",
        "Group": null,
        "HomeTeamScore": 6,
        "AwayTeamScore": 5
    },
    {
        "MatchNumber": 1298,
        "RoundNumber": 15,
        "DateUtc": "2023-07-05 23:10:00Z",
        "Location": "Progressive Field",
        "HomeTeam": "Cleveland Guardians",
        "AwayTeam": "Atlanta Braves",
        "Group": null,
        "HomeTeamScore": 1,
        "AwayTeamScore": 8
    },
    {
        "MatchNumber": 1312,
        "RoundNumber": 15,
        "DateUtc": "2023-07-06 23:10:00Z",
        "Location": "Progressive Field",
        "HomeTeam": "Cleveland Guardians",
        "AwayTeam": "Kansas City Royals",
        "Group": null,
        "HomeTeamScore": 6,
        "AwayTeamScore": 1
    },
    {
        "MatchNumber": 1323,
        "RoundNumber": 15,
        "DateUtc": "2023-07-07 23:10:00Z",
        "Location": "Progressive Field",
        "HomeTeam": "Cleveland Guardians",
        "AwayTeam": "Kansas City Royals",
        "Group": null,
        "HomeTeamScore": 3,
        "AwayTeamScore": 0
    },
    {
        "MatchNumber": 1339,
        "RoundNumber": 15,
        "DateUtc": "2023-07-08 20:10:00Z",
        "Location": "Progressive Field",
        "HomeTeam": "Cleveland Guardians",
        "AwayTeam": "Kansas City Royals",
        "Group": null,
        "HomeTeamScore": 10,
        "AwayTeamScore": 6
    },
    {
        "MatchNumber": 1351,
        "RoundNumber": 15,
        "DateUtc": "2023-07-09 17:40:00Z",
        "Location": "Progressive Field",
        "HomeTeam": "Cleveland Guardians",
        "AwayTeam": "Kansas City Royals",
        "Group": null,
        "HomeTeamScore": 1,
        "AwayTeamScore": 4
    },
    {
        "MatchNumber": 1370,
        "RoundNumber": 16,
        "DateUtc": "2023-07-15 00:05:00Z",
        "Location": "Globe Life Field",
        "HomeTeam": "Texas Rangers",
        "AwayTeam": "Cleveland Guardians",
        "Group": null,
        "HomeTeamScore": 12,
        "AwayTeamScore": 4
    },
    {
        "MatchNumber": 1381,
        "RoundNumber": 16,
        "DateUtc": "2023-07-15 20:05:00Z",
        "Location": "Globe Life Field",
        "HomeTeam": "Texas Rangers",
        "AwayTeam": "Cleveland Guardians",
        "Group": null,
        "HomeTeamScore": 2,
        "AwayTeamScore": 0
    },
    {
        "MatchNumber": 1403,
        "RoundNumber": 16,
        "DateUtc": "2023-07-16 18:35:00Z",
        "Location": "Globe Life Field",
        "HomeTeam": "Texas Rangers",
        "AwayTeam": "Cleveland Guardians",
        "Group": null,
        "HomeTeamScore": 6,
        "AwayTeamScore": 5
    },
    {
        "MatchNumber": 1409,
        "RoundNumber": 16,
        "DateUtc": "2023-07-17 23:05:00Z",
        "Location": "PNC Park",
        "HomeTeam": "Pittsburgh Pirates",
        "AwayTeam": "Cleveland Guardians",
        "Group": null,
        "HomeTeamScore": 0,
        "AwayTeamScore": 11
    },
    {
        "MatchNumber": 1420,
        "RoundNumber": 16,
        "DateUtc": "2023-07-18 23:05:00Z",
        "Location": "PNC Park",
        "HomeTeam": "Pittsburgh Pirates",
        "AwayTeam": "Cleveland Guardians",
        "Group": null,
        "HomeTeamScore": 1,
        "AwayTeamScore": 10
    },
    {
        "MatchNumber": 1433,
        "RoundNumber": 17,
        "DateUtc": "2023-07-19 16:35:00Z",
        "Location": "PNC Park",
        "HomeTeam": "Pittsburgh Pirates",
        "AwayTeam": "Cleveland Guardians",
        "Group": null,
        "HomeTeamScore": 7,
        "AwayTeamScore": 5
    },
    {
        "MatchNumber": 1466,
        "RoundNumber": 17,
        "DateUtc": "2023-07-21 23:10:00Z",
        "Location": "Progressive Field",
        "HomeTeam": "Cleveland Guardians",
        "AwayTeam": "Philadelphia Phillies",
        "Group": null,
        "HomeTeamScore": 6,
        "AwayTeamScore": 5
    },
    {
        "MatchNumber": 1483,
        "RoundNumber": 17,
        "DateUtc": "2023-07-22 23:10:00Z",
        "Location": "Progressive Field",
        "HomeTeam": "Cleveland Guardians",
        "AwayTeam": "Philadelphia Phillies",
        "Group": null,
        "HomeTeamScore": 1,
        "AwayTeamScore": 0
    },
    {
        "MatchNumber": 1493,
        "RoundNumber": 17,
        "DateUtc": "2023-07-23 17:40:00Z",
        "Location": "Progressive Field",
        "HomeTeam": "Cleveland Guardians",
        "AwayTeam": "Philadelphia Phillies",
        "Group": null,
        "HomeTeamScore": 5,
        "AwayTeamScore": 8
    },
    {
        "MatchNumber": 1505,
        "RoundNumber": 17,
        "DateUtc": "2023-07-24 23:10:00Z",
        "Location": "Progressive Field",
        "HomeTeam": "Cleveland Guardians",
        "AwayTeam": "Kansas City Royals",
        "Group": null,
        "HomeTeamScore": 3,
        "AwayTeamScore": 5
    },
    {
        "MatchNumber": 1517,
        "RoundNumber": 17,
        "DateUtc": "2023-07-25 23:10:00Z",
        "Location": "Progressive Field",
        "HomeTeam": "Cleveland Guardians",
        "AwayTeam": "Kansas City Royals",
        "Group": null,
        "HomeTeamScore": 5,
        "AwayTeamScore": 1
    },
    {
        "MatchNumber": 1529,
        "RoundNumber": 18,
        "DateUtc": "2023-07-26 17:10:00Z",
        "Location": "Progressive Field",
        "HomeTeam": "Cleveland Guardians",
        "AwayTeam": "Kansas City Royals",
        "Group": null,
        "HomeTeamScore": 8,
        "AwayTeamScore": 3
    },
    {
        "MatchNumber": 1545,
        "RoundNumber": 18,
        "DateUtc": "2023-07-28 00:10:00Z",
        "Location": "Guaranteed Rate Field",
        "HomeTeam": "Chicago White Sox",
        "AwayTeam": "Cleveland Guardians",
        "Group": null,
        "HomeTeamScore": 3,
        "AwayTeamScore": 6
    },
    {
        "MatchNumber": 1551,
        "RoundNumber": 18,
        "DateUtc": "2023-07-28 23:10:00Z",
        "Location": "Guaranteed Rate Field",
        "HomeTeam": "Chicago White Sox",
        "AwayTeam": "Cleveland Guardians",
        "Group": null,
        "HomeTeamScore": 3,
        "AwayTeamScore": 0
    },
    {
        "MatchNumber": 1567,
        "RoundNumber": 18,
        "DateUtc": "2023-07-29 23:10:00Z",
        "Location": "Guaranteed Rate Field",
        "HomeTeam": "Chicago White Sox",
        "AwayTeam": "Cleveland Guardians",
        "Group": null,
        "HomeTeamScore": 7,
        "AwayTeamScore": 2
    },
    {
        "MatchNumber": 1584,
        "RoundNumber": 18,
        "DateUtc": "2023-07-30 18:10:00Z",
        "Location": "Guaranteed Rate Field",
        "HomeTeam": "Chicago White Sox",
        "AwayTeam": "Cleveland Guardians",
        "Group": null,
        "HomeTeamScore": 0,
        "AwayTeamScore": 5
    },
    {
        "MatchNumber": 1597,
        "RoundNumber": 18,
        "DateUtc": "2023-08-01 00:10:00Z",
        "Location": "Minute Maid Park",
        "HomeTeam": "Houston Astros",
        "AwayTeam": "Cleveland Guardians",
        "Group": null,
        "HomeTeamScore": 7,
        "AwayTeamScore": 3
    },
    {
        "MatchNumber": 1610,
        "RoundNumber": 18,
        "DateUtc": "2023-08-02 00:10:00Z",
        "Location": "Minute Maid Park",
        "HomeTeam": "Houston Astros",
        "AwayTeam": "Cleveland Guardians",
        "Group": null,
        "HomeTeamScore": 2,
        "AwayTeamScore": 0
    },
    {
        "MatchNumber": 1619,
        "RoundNumber": 19,
        "DateUtc": "2023-08-02 18:10:00Z",
        "Location": "Minute Maid Park",
        "HomeTeam": "Houston Astros",
        "AwayTeam": "Cleveland Guardians",
        "Group": null,
        "HomeTeamScore": 3,
        "AwayTeamScore": 2
    },
    {
        "MatchNumber": 1649,
        "RoundNumber": 19,
        "DateUtc": "2023-08-04 23:10:00Z",
        "Location": "Progressive Field",
        "HomeTeam": "Cleveland Guardians",
        "AwayTeam": "Chicago White Sox",
        "Group": null,
        "HomeTeamScore": 4,
        "AwayTeamScore": 2
    },
    {
        "MatchNumber": 1666,
        "RoundNumber": 19,
        "DateUtc": "2023-08-05 23:10:00Z",
        "Location": "Progressive Field",
        "HomeTeam": "Cleveland Guardians",
        "AwayTeam": "Chicago White Sox",
        "Group": null,
        "HomeTeamScore": 4,
        "AwayTeamScore": 7
    },
    {
        "MatchNumber": 1671,
        "RoundNumber": 19,
        "DateUtc": "2023-08-06 16:05:00Z",
        "Location": "Progressive Field",
        "HomeTeam": "Cleveland Guardians",
        "AwayTeam": "Chicago White Sox",
        "Group": null,
        "HomeTeamScore": 3,
        "AwayTeamScore": 5
    },
    {
        "MatchNumber": 1693,
        "RoundNumber": 19,
        "DateUtc": "2023-08-07 23:10:00Z",
        "Location": "Progressive Field",
        "HomeTeam": "Cleveland Guardians",
        "AwayTeam": "Toronto Blue Jays",
        "Group": null,
        "HomeTeamScore": 1,
        "AwayTeamScore": 2
    },
    {
        "MatchNumber": 1706,
        "RoundNumber": 19,
        "DateUtc": "2023-08-08 23:10:00Z",
        "Location": "Progressive Field",
        "HomeTeam": "Cleveland Guardians",
        "AwayTeam": "Toronto Blue Jays",
        "Group": null,
        "HomeTeamScore": 1,
        "AwayTeamScore": 0
    },
    {
        "MatchNumber": 1723,
        "RoundNumber": 20,
        "DateUtc": "2023-08-09 23:10:00Z",
        "Location": "Progressive Field",
        "HomeTeam": "Cleveland Guardians",
        "AwayTeam": "Toronto Blue Jays",
        "Group": null,
        "HomeTeamScore": 0,
        "AwayTeamScore": 1
    },
    {
        "MatchNumber": 1730,
        "RoundNumber": 20,
        "DateUtc": "2023-08-10 17:10:00Z",
        "Location": "Progressive Field",
        "HomeTeam": "Cleveland Guardians",
        "AwayTeam": "Toronto Blue Jays",
        "Group": null,
        "HomeTeamScore": 4,
        "AwayTeamScore": 3
    },
    {
        "MatchNumber": 1736,
        "RoundNumber": 20,
        "DateUtc": "2023-08-11 22:40:00Z",
        "Location": "Tropicana Field",
        "HomeTeam": "Tampa Bay Rays",
        "AwayTeam": "Cleveland Guardians",
        "Group": null,
        "HomeTeamScore": 9,
        "AwayTeamScore": 8
    },
    {
        "MatchNumber": 1753,
        "RoundNumber": 20,
        "DateUtc": "2023-08-12 20:10:00Z",
        "Location": "Tropicana Field",
        "HomeTeam": "Tampa Bay Rays",
        "AwayTeam": "Cleveland Guardians",
        "Group": null,
        "HomeTeamScore": 6,
        "AwayTeamScore": 5
    },
    {
        "MatchNumber": 1771,
        "RoundNumber": 20,
        "DateUtc": "2023-08-13 17:40:00Z",
        "Location": "Tropicana Field",
        "HomeTeam": "Tampa Bay Rays",
        "AwayTeam": "Cleveland Guardians",
        "Group": null,
        "HomeTeamScore": 2,
        "AwayTeamScore": 9
    },
    {
        "MatchNumber": 1789,
        "RoundNumber": 20,
        "DateUtc": "2023-08-15 22:40:00Z",
        "Location": "Great American Ball Park",
        "HomeTeam": "Cincinnati Reds",
        "AwayTeam": "Cleveland Guardians",
        "Group": null,
        "HomeTeamScore": 0,
        "AwayTeamScore": 3
    },
    {
        "MatchNumber": 1808,
        "RoundNumber": 21,
        "DateUtc": "2023-08-16 22:40:00Z",
        "Location": "Great American Ball Park",
        "HomeTeam": "Cincinnati Reds",
        "AwayTeam": "Cleveland Guardians",
        "Group": null,
        "HomeTeamScore": 7,
        "AwayTeamScore": 2
    },
    {
        "MatchNumber": 1821,
        "RoundNumber": 21,
        "DateUtc": "2023-08-18 20:15:00Z",
        "Location": "Progressive Field",
        "HomeTeam": "Cleveland Guardians",
        "AwayTeam": "Detroit Tigers",
        "Group": null,
        "HomeTeamScore": 4,
        "AwayTeamScore": 1
    },
    {
        "MatchNumber": 1829,
        "RoundNumber": 21,
        "DateUtc": "2023-08-18 22:10:00Z",
        "Location": "Progressive Field",
        "HomeTeam": "Cleveland Guardians",
        "AwayTeam": "Detroit Tigers",
        "Group": null,
        "HomeTeamScore": 2,
        "AwayTeamScore": 4
    },
    {
        "MatchNumber": 1845,
        "RoundNumber": 21,
        "DateUtc": "2023-08-19 23:10:00Z",
        "Location": "Progressive Field",
        "HomeTeam": "Cleveland Guardians",
        "AwayTeam": "Detroit Tigers",
        "Group": null,
        "HomeTeamScore": 3,
        "AwayTeamScore": 4
    },
    {
        "MatchNumber": 1858,
        "RoundNumber": 21,
        "DateUtc": "2023-08-20 17:40:00Z",
        "Location": "Progressive Field",
        "HomeTeam": "Cleveland Guardians",
        "AwayTeam": "Detroit Tigers",
        "Group": null,
        "HomeTeamScore": 1,
        "AwayTeamScore": 4
    },
    {
        "MatchNumber": 1886,
        "RoundNumber": 21,
        "DateUtc": "2023-08-22 23:10:00Z",
        "Location": "Progressive Field",
        "HomeTeam": "Cleveland Guardians",
        "AwayTeam": "Los Angeles Dodgers",
        "Group": null,
        "HomeTeamScore": 8,
        "AwayTeamScore": 3
    },
    {
        "MatchNumber": 1906,
        "RoundNumber": 22,
        "DateUtc": "2023-08-23 23:10:00Z",
        "Location": "Progressive Field",
        "HomeTeam": "Cleveland Guardians",
        "AwayTeam": "Los Angeles Dodgers",
        "Group": null,
        "HomeTeamScore": 1,
        "AwayTeamScore": 6
    },
    {
        "MatchNumber": 1910,
        "RoundNumber": 22,
        "DateUtc": "2023-08-24 20:20:00Z",
        "Location": "Progressive Field",
        "HomeTeam": "Cleveland Guardians",
        "AwayTeam": "Los Angeles Dodgers",
        "Group": null,
        "HomeTeamScore": 3,
        "AwayTeamScore": 9
    },
    {
        "MatchNumber": 1924,
        "RoundNumber": 22,
        "DateUtc": "2023-08-25 23:07:00Z",
        "Location": "Rogers Centre",
        "HomeTeam": "Toronto Blue Jays",
        "AwayTeam": "Cleveland Guardians",
        "Group": null,
        "HomeTeamScore": 2,
        "AwayTeamScore": 5
    },
    {
        "MatchNumber": 1933,
        "RoundNumber": 22,
        "DateUtc": "2023-08-26 19:07:00Z",
        "Location": "Rogers Centre",
        "HomeTeam": "Toronto Blue Jays",
        "AwayTeam": "Cleveland Guardians",
        "Group": null,
        "HomeTeamScore": 8,
        "AwayTeamScore": 3
    },
    {
        "MatchNumber": 1952,
        "RoundNumber": 22,
        "DateUtc": "2023-08-27 17:37:00Z",
        "Location": "Rogers Centre",
        "HomeTeam": "Toronto Blue Jays",
        "AwayTeam": "Cleveland Guardians",
        "Group": null,
        "HomeTeamScore": 7,
        "AwayTeamScore": 10
    },
    {
        "MatchNumber": 1969,
        "RoundNumber": 22,
        "DateUtc": "2023-08-28 23:40:00Z",
        "Location": "Target Field",
        "HomeTeam": "Minnesota Twins",
        "AwayTeam": "Cleveland Guardians",
        "Group": null,
        "HomeTeamScore": 10,
        "AwayTeamScore": 6
    },
    {
        "MatchNumber": 1984,
        "RoundNumber": 22,
        "DateUtc": "2023-08-29 23:40:00Z",
        "Location": "Target Field",
        "HomeTeam": "Minnesota Twins",
        "AwayTeam": "Cleveland Guardians",
        "Group": null,
        "HomeTeamScore": 2,
        "AwayTeamScore": 4
    },
    {
        "MatchNumber": 1994,
        "RoundNumber": 23,
        "DateUtc": "2023-08-30 17:10:00Z",
        "Location": "Target Field",
        "HomeTeam": "Minnesota Twins",
        "AwayTeam": "Cleveland Guardians",
        "Group": null,
        "HomeTeamScore": 2,
        "AwayTeamScore": 5
    },
    {
        "MatchNumber": 2014,
        "RoundNumber": 23,
        "DateUtc": "2023-09-01 23:10:00Z",
        "Location": "Progressive Field",
        "HomeTeam": "Cleveland Guardians",
        "AwayTeam": "Tampa Bay Rays",
        "Group": null,
        "HomeTeamScore": 3,
        "AwayTeamScore": 2
    },
    {
        "MatchNumber": 2028,
        "RoundNumber": 23,
        "DateUtc": "2023-09-02 22:10:00Z",
        "Location": "Progressive Field",
        "HomeTeam": "Cleveland Guardians",
        "AwayTeam": "Tampa Bay Rays",
        "Group": null,
        "HomeTeamScore": 7,
        "AwayTeamScore": 6
    },
    {
        "MatchNumber": 2054,
        "RoundNumber": 23,
        "DateUtc": "2023-09-03 20:10:00Z",
        "Location": "Progressive Field",
        "HomeTeam": "Cleveland Guardians",
        "AwayTeam": "Tampa Bay Rays",
        "Group": null,
        "HomeTeamScore": 2,
        "AwayTeamScore": 6
    },
    {
        "MatchNumber": 2062,
        "RoundNumber": 23,
        "DateUtc": "2023-09-04 22:10:00Z",
        "Location": "Progressive Field",
        "HomeTeam": "Cleveland Guardians",
        "AwayTeam": "Minnesota Twins",
        "Group": null,
        "HomeTeamScore": 6,
        "AwayTeamScore": 20
    },
    {
        "MatchNumber": 2066,
        "RoundNumber": 23,
        "DateUtc": "2023-09-05 22:10:00Z",
        "Location": "Progressive Field",
        "HomeTeam": "Cleveland Guardians",
        "AwayTeam": "Minnesota Twins",
        "Group": null,
        "HomeTeamScore": 3,
        "AwayTeamScore": 8
    },
    {
        "MatchNumber": 2082,
        "RoundNumber": 24,
        "DateUtc": "2023-09-06 17:10:00Z",
        "Location": "Progressive Field",
        "HomeTeam": "Cleveland Guardians",
        "AwayTeam": "Minnesota Twins",
        "Group": null,
        "HomeTeamScore": 2,
        "AwayTeamScore": 1
    },
    {
        "MatchNumber": 2102,
        "RoundNumber": 24,
        "DateUtc": "2023-09-08 01:38:00Z",
        "Location": "Angel Stadium",
        "HomeTeam": "Los Angeles Angels",
        "AwayTeam": "Cleveland Guardians",
        "Group": null,
        "HomeTeamScore": 3,
        "AwayTeamScore": 2
    },
    {
        "MatchNumber": 2116,
        "RoundNumber": 24,
        "DateUtc": "2023-09-09 01:38:00Z",
        "Location": "Angel Stadium",
        "HomeTeam": "Los Angeles Angels",
        "AwayTeam": "Cleveland Guardians",
        "Group": null,
        "HomeTeamScore": 3,
        "AwayTeamScore": 6
    },
    {
        "MatchNumber": 2132,
        "RoundNumber": 24,
        "DateUtc": "2023-09-10 01:07:00Z",
        "Location": "Angel Stadium",
        "HomeTeam": "Los Angeles Angels",
        "AwayTeam": "Cleveland Guardians",
        "Group": null,
        "HomeTeamScore": 6,
        "AwayTeamScore": 2
    },
    {
        "MatchNumber": 2147,
        "RoundNumber": 24,
        "DateUtc": "2023-09-10 20:07:00Z",
        "Location": "Angel Stadium",
        "HomeTeam": "Los Angeles Angels",
        "AwayTeam": "Cleveland Guardians",
        "Group": null,
        "HomeTeamScore": 2,
        "AwayTeamScore": 1
    },
    {
        "MatchNumber": 2159,
        "RoundNumber": 24,
        "DateUtc": "2023-09-12 01:45:00Z",
        "Location": "Oracle Park",
        "HomeTeam": "San Francisco Giants",
        "AwayTeam": "Cleveland Guardians",
        "Group": null,
        "HomeTeamScore": 5,
        "AwayTeamScore": 4
    },
    {
        "MatchNumber": 2174,
        "RoundNumber": 24,
        "DateUtc": "2023-09-13 01:45:00Z",
        "Location": "Oracle Park",
        "HomeTeam": "San Francisco Giants",
        "AwayTeam": "Cleveland Guardians",
        "Group": null,
        "HomeTeamScore": 1,
        "AwayTeamScore": 3
    },
    {
        "MatchNumber": 2178,
        "RoundNumber": 25,
        "DateUtc": "2023-09-13 19:45:00Z",
        "Location": "Oracle Park",
        "HomeTeam": "San Francisco Giants",
        "AwayTeam": "Cleveland Guardians",
        "Group": null,
        "HomeTeamScore": 6,
        "AwayTeamScore": 5
    },
    {
        "MatchNumber": 2206,
        "RoundNumber": 25,
        "DateUtc": "2023-09-15 23:10:00Z",
        "Location": "Progressive Field",
        "HomeTeam": "Cleveland Guardians",
        "AwayTeam": "Texas Rangers",
        "Group": null,
        "HomeTeamScore": 12,
        "AwayTeamScore": 3
    },
    {
        "MatchNumber": 2219,
        "RoundNumber": 25,
        "DateUtc": "2023-09-16 22:10:00Z",
        "Location": "Progressive Field",
        "HomeTeam": "Cleveland Guardians",
        "AwayTeam": "Texas Rangers",
        "Group": null,
        "HomeTeamScore": 2,
        "AwayTeamScore": 1
    },
    {
        "MatchNumber": 2235,
        "RoundNumber": 25,
        "DateUtc": "2023-09-17 17:40:00Z",
        "Location": "Progressive Field",
        "HomeTeam": "Cleveland Guardians",
        "AwayTeam": "Texas Rangers",
        "Group": null,
        "HomeTeamScore": 9,
        "AwayTeamScore": 2
    },
    {
        "MatchNumber": 2246,
        "RoundNumber": 25,
        "DateUtc": "2023-09-18 18:10:00Z",
        "Location": "Kauffman Stadium",
        "HomeTeam": "Kansas City Royals",
        "AwayTeam": "Cleveland Guardians",
        "Group": null,
        "HomeTeamScore": 6,
        "AwayTeamScore": 4
    },
    {
        "MatchNumber": 2263,
        "RoundNumber": 25,
        "DateUtc": "2023-09-19 23:40:00Z",
        "Location": "Kauffman Stadium",
        "HomeTeam": "Kansas City Royals",
        "AwayTeam": "Cleveland Guardians",
        "Group": null,
        "HomeTeamScore": 7,
        "AwayTeamScore": 6
    },
    {
        "MatchNumber": 2277,
        "RoundNumber": 26,
        "DateUtc": "2023-09-20 18:10:00Z",
        "Location": "Kauffman Stadium",
        "HomeTeam": "Kansas City Royals",
        "AwayTeam": "Cleveland Guardians",
        "Group": null,
        "HomeTeamScore": 6,
        "AwayTeamScore": 2
    },
    {
        "MatchNumber": 2292,
        "RoundNumber": 26,
        "DateUtc": "2023-09-21 23:15:00Z",
        "Location": "Progressive Field",
        "HomeTeam": "Cleveland Guardians",
        "AwayTeam": "Baltimore Orioles",
        "Group": null,
        "HomeTeamScore": 5,
        "AwayTeamScore": 2
    },
    {
        "MatchNumber": 2303,
        "RoundNumber": 26,
        "DateUtc": "2023-09-22 23:10:00Z",
        "Location": "Progressive Field",
        "HomeTeam": "Cleveland Guardians",
        "AwayTeam": "Baltimore Orioles",
        "Group": null,
        "HomeTeamScore": 9,
        "AwayTeamScore": 8
    },
    {
        "MatchNumber": 2320,
        "RoundNumber": 26,
        "DateUtc": "2023-09-23 22:10:00Z",
        "Location": "Progressive Field",
        "HomeTeam": "Cleveland Guardians",
        "AwayTeam": "Baltimore Orioles",
        "Group": null,
        "HomeTeamScore": 1,
        "AwayTeamScore": 2
    },
    {
        "MatchNumber": 2331,
        "RoundNumber": 26,
        "DateUtc": "2023-09-24 17:40:00Z",
        "Location": "Progressive Field",
        "HomeTeam": "Cleveland Guardians",
        "AwayTeam": "Baltimore Orioles",
        "Group": null,
        "HomeTeamScore": 1,
        "AwayTeamScore": 5
    },
    {
        "MatchNumber": 2347,
        "RoundNumber": 26,
        "DateUtc": "2023-09-26 22:10:00Z",
        "Location": "Progressive Field",
        "HomeTeam": "Cleveland Guardians",
        "AwayTeam": "Cincinnati Reds",
        "Group": null,
        "HomeTeamScore": 7,
        "AwayTeamScore": 11
    },
    {
        "MatchNumber": 2362,
        "RoundNumber": 27,
        "DateUtc": "2023-09-27 22:10:00Z",
        "Location": "Progressive Field",
        "HomeTeam": "Cleveland Guardians",
        "AwayTeam": "Cincinnati Reds",
        "Group": null,
        "HomeTeamScore": 4,
        "AwayTeamScore": 3
    },
    {
        "MatchNumber": 2387,
        "RoundNumber": 27,
        "DateUtc": "2023-09-29 22:40:00Z",
        "Location": "Comerica Park",
        "HomeTeam": "Detroit Tigers",
        "AwayTeam": "Cleveland Guardians",
        "Group": null,
        "HomeTeamScore": 5,
        "AwayTeamScore": 7
    },
    {
        "MatchNumber": 2401,
        "RoundNumber": 27,
        "DateUtc": "2023-09-30 17:10:00Z",
        "Location": "Comerica Park",
        "HomeTeam": "Detroit Tigers",
        "AwayTeam": "Cleveland Guardians",
        "Group": null,
        "HomeTeamScore": 8,
        "AwayTeamScore": 0
    },
    {
        "MatchNumber": 2422,
        "RoundNumber": 27,
        "DateUtc": "2023-10-01 19:10:00Z",
        "Location": "Comerica Park",
        "HomeTeam": "Detroit Tigers",
        "AwayTeam": "Cleveland Guardians",
        "Group": null,
        "HomeTeamScore": 5,
        "AwayTeamScore": 2
    }
]