[
    {
        "team": "Los Angeles Dodgers"
    },
    {
        "MatchNumber": 1,
        "RoundNumber": 1,
        "DateUtc": "2024-03-20 10:05:00Z",
        "Location": "Gocheok Sky Dome",
        "HomeTeam": "San Diego Padres",
        "AwayTeam": "Los Angeles Dodgers",
        "Group": null,
        "HomeTeamScore": 2,
        "AwayTeamScore": 5
    },
    {
        "MatchNumber": 2,
        "RoundNumber": 1,
        "DateUtc": "2024-03-21 10:05:00Z",
        "Location": "Gocheok Sky Dome",
        "HomeTeam": "Los Angeles Dodgers",
        "AwayTeam": "San Diego Padres",
        "Group": null,
        "HomeTeamScore": 11,
        "AwayTeamScore": 15
    },
    {
        "MatchNumber": 8,
        "RoundNumber": 1,
        "DateUtc": "2024-03-28 20:10:00Z",
        "Location": "Dodger Stadium",
        "HomeTeam": "Los Angeles Dodgers",
        "AwayTeam": "St. Louis Cardinals",
        "Group": null,
        "HomeTeamScore": 7,
        "AwayTeamScore": 1
    },
    {
        "MatchNumber": 25,
        "RoundNumber": 1,
        "DateUtc": "2024-03-30 02:10:00Z",
        "Location": "Dodger Stadium",
        "HomeTeam": "Los Angeles Dodgers",
        "AwayTeam": "St. Louis Cardinals",
        "Group": null,
        "HomeTeamScore": 6,
        "AwayTeamScore": 3
    },
    {
        "MatchNumber": 39,
        "RoundNumber": 1,
        "DateUtc": "2024-03-31 01:10:00Z",
        "Location": "Dodger Stadium",
        "HomeTeam": "Los Angeles Dodgers",
        "AwayTeam": "St. Louis Cardinals",
        "Group": null,
        "HomeTeamScore": 5,
        "AwayTeamScore": 6
    },
    {
        "MatchNumber": 55,
        "RoundNumber": 1,
        "DateUtc": "2024-03-31 23:10:00Z",
        "Location": "Dodger Stadium",
        "HomeTeam": "Los Angeles Dodgers",
        "AwayTeam": "St. Louis Cardinals",
        "Group": null,
        "HomeTeamScore": 5,
        "AwayTeamScore": 4
    },
    {
        "MatchNumber": 69,
        "RoundNumber": 1,
        "DateUtc": "2024-04-02 02:10:00Z",
        "Location": "Dodger Stadium",
        "HomeTeam": "Los Angeles Dodgers",
        "AwayTeam": "San Francisco Giants",
        "Group": null,
        "HomeTeamScore": 8,
        "AwayTeamScore": 3
    },
    {
        "MatchNumber": 83,
        "RoundNumber": 1,
        "DateUtc": "2024-04-03 02:10:00Z",
        "Location": "Dodger Stadium",
        "HomeTeam": "Los Angeles Dodgers",
        "AwayTeam": "San Francisco Giants",
        "Group": null,
        "HomeTeamScore": 5,
        "AwayTeamScore": 4
    },
    {
        "MatchNumber": 98,
        "RoundNumber": 2,
        "DateUtc": "2024-04-04 02:10:00Z",
        "Location": "Dodger Stadium",
        "HomeTeam": "Los Angeles Dodgers",
        "AwayTeam": "San Francisco Giants",
        "Group": null,
        "HomeTeamScore": 5,
        "AwayTeamScore": 4
    },
    {
        "MatchNumber": 105,
        "RoundNumber": 2,
        "DateUtc": "2024-04-05 18:20:00Z",
        "Location": "Wrigley Field",
        "HomeTeam": "Chicago Cubs",
        "AwayTeam": "Los Angeles Dodgers",
        "Group": null,
        "HomeTeamScore": 9,
        "AwayTeamScore": 7
    },
    {
        "MatchNumber": 119,
        "RoundNumber": 2,
        "DateUtc": "2024-04-06 20:05:00Z",
        "Location": "Wrigley Field",
        "HomeTeam": "Chicago Cubs",
        "AwayTeam": "Los Angeles Dodgers",
        "Group": null,
        "HomeTeamScore": 1,
        "AwayTeamScore": 4
    },
    {
        "MatchNumber": 141,
        "RoundNumber": 2,
        "DateUtc": "2024-04-07 18:20:00Z",
        "Location": "Wrigley Field",
        "HomeTeam": "Chicago Cubs",
        "AwayTeam": "Los Angeles Dodgers",
        "Group": null,
        "HomeTeamScore": 8,
        "AwayTeamScore": 1
    },
    {
        "MatchNumber": 151,
        "RoundNumber": 2,
        "DateUtc": "2024-04-08 23:40:00Z",
        "Location": "Target Field",
        "HomeTeam": "Minnesota Twins",
        "AwayTeam": "Los Angeles Dodgers",
        "Group": null,
        "HomeTeamScore": 2,
        "AwayTeamScore": 4
    },
    {
        "MatchNumber": 167,
        "RoundNumber": 2,
        "DateUtc": "2024-04-09 23:40:00Z",
        "Location": "Target Field",
        "HomeTeam": "Minnesota Twins",
        "AwayTeam": "Los Angeles Dodgers",
        "Group": null,
        "HomeTeamScore": 3,
        "AwayTeamScore": 6
    },
    {
        "MatchNumber": 174,
        "RoundNumber": 3,
        "DateUtc": "2024-04-10 17:10:00Z",
        "Location": "Target Field",
        "HomeTeam": "Minnesota Twins",
        "AwayTeam": "Los Angeles Dodgers",
        "Group": null,
        "HomeTeamScore": 3,
        "AwayTeamScore": 2
    },
    {
        "MatchNumber": 209,
        "RoundNumber": 3,
        "DateUtc": "2024-04-13 02:10:00Z",
        "Location": "Dodger Stadium",
        "HomeTeam": "Los Angeles Dodgers",
        "AwayTeam": "San Diego Padres",
        "Group": null,
        "HomeTeamScore": 7,
        "AwayTeamScore": 8
    },
    {
        "MatchNumber": 223,
        "RoundNumber": 3,
        "DateUtc": "2024-04-14 01:10:00Z",
        "Location": "Dodger Stadium",
        "HomeTeam": "Los Angeles Dodgers",
        "AwayTeam": "San Diego Padres",
        "Group": null,
        "HomeTeamScore": 5,
        "AwayTeamScore": 2
    },
    {
        "MatchNumber": 239,
        "RoundNumber": 3,
        "DateUtc": "2024-04-14 23:10:00Z",
        "Location": "Dodger Stadium",
        "HomeTeam": "Los Angeles Dodgers",
        "AwayTeam": "San Diego Padres",
        "Group": null,
        "HomeTeamScore": 3,
        "AwayTeamScore": 6
    },
    {
        "MatchNumber": 254,
        "RoundNumber": 3,
        "DateUtc": "2024-04-16 02:10:00Z",
        "Location": "Dodger Stadium",
        "HomeTeam": "Los Angeles Dodgers",
        "AwayTeam": "Washington Nationals",
        "Group": null,
        "HomeTeamScore": null,
        "AwayTeamScore": null
    },
    {
        "MatchNumber": 269,
        "RoundNumber": 3,
        "DateUtc": "2024-04-17 02:10:00Z",
        "Location": "Dodger Stadium",
        "HomeTeam": "Los Angeles Dodgers",
        "AwayTeam": "Washington Nationals",
        "Group": null,
        "HomeTeamScore": null,
        "AwayTeamScore": null
    },
    {
        "MatchNumber": 278,
        "RoundNumber": 4,
        "DateUtc": "2024-04-17 19:10:00Z",
        "Location": "Dodger Stadium",
        "HomeTeam": "Los Angeles Dodgers",
        "AwayTeam": "Washington Nationals",
        "Group": null,
        "HomeTeamScore": null,
        "AwayTeamScore": null
    },
    {
        "MatchNumber": 303,
        "RoundNumber": 4,
        "DateUtc": "2024-04-20 02:10:00Z",
        "Location": "Dodger Stadium",
        "HomeTeam": "Los Angeles Dodgers",
        "AwayTeam": "New York Mets",
        "Group": null,
        "HomeTeamScore": null,
        "AwayTeamScore": null
    },
    {
        "MatchNumber": 310,
        "RoundNumber": 4,
        "DateUtc": "2024-04-20 20:05:00Z",
        "Location": "Dodger Stadium",
        "HomeTeam": "Los Angeles Dodgers",
        "AwayTeam": "New York Mets",
        "Group": null,
        "HomeTeamScore": null,
        "AwayTeamScore": null
    },
    {
        "MatchNumber": 332,
        "RoundNumber": 4,
        "DateUtc": "2024-04-21 20:10:00Z",
        "Location": "Dodger Stadium",
        "HomeTeam": "Los Angeles Dodgers",
        "AwayTeam": "New York Mets",
        "Group": null,
        "HomeTeamScore": null,
        "AwayTeamScore": null
    },
    {
        "MatchNumber": 349,
        "RoundNumber": 4,
        "DateUtc": "2024-04-23 22:45:00Z",
        "Location": "Nationals Park",
        "HomeTeam": "Washington Nationals",
        "AwayTeam": "Los Angeles Dodgers",
        "Group": null,
        "HomeTeamScore": null,
        "AwayTeamScore": null
    },
    {
        "MatchNumber": 367,
        "RoundNumber": 5,
        "DateUtc": "2024-04-24 22:45:00Z",
        "Location": "Nationals Park",
        "HomeTeam": "Washington Nationals",
        "AwayTeam": "Los Angeles Dodgers",
        "Group": null,
        "HomeTeamScore": null,
        "AwayTeamScore": null
    },
    {
        "MatchNumber": 384,
        "RoundNumber": 5,
        "DateUtc": "2024-04-25 20:05:00Z",
        "Location": "Nationals Park",
        "HomeTeam": "Washington Nationals",
        "AwayTeam": "Los Angeles Dodgers",
        "Group": null,
        "HomeTeamScore": null,
        "AwayTeamScore": null
    },
    {
        "MatchNumber": 388,
        "RoundNumber": 5,
        "DateUtc": "2024-04-26 23:07:00Z",
        "Location": "Rogers Centre",
        "HomeTeam": "Toronto Blue Jays",
        "AwayTeam": "Los Angeles Dodgers",
        "Group": null,
        "HomeTeamScore": null,
        "AwayTeamScore": null
    },
    {
        "MatchNumber": 400,
        "RoundNumber": 5,
        "DateUtc": "2024-04-27 19:07:00Z",
        "Location": "Rogers Centre",
        "HomeTeam": "Toronto Blue Jays",
        "AwayTeam": "Los Angeles Dodgers",
        "Group": null,
        "HomeTeamScore": null,
        "AwayTeamScore": null
    },
    {
        "MatchNumber": 417,
        "RoundNumber": 5,
        "DateUtc": "2024-04-28 17:37:00Z",
        "Location": "Rogers Centre",
        "HomeTeam": "Toronto Blue Jays",
        "AwayTeam": "Los Angeles Dodgers",
        "Group": null,
        "HomeTeamScore": null,
        "AwayTeamScore": null
    },
    {
        "MatchNumber": 438,
        "RoundNumber": 5,
        "DateUtc": "2024-04-30 01:40:00Z",
        "Location": "Chase Field",
        "HomeTeam": "Arizona Diamondbacks",
        "AwayTeam": "Los Angeles Dodgers",
        "Group": null,
        "HomeTeamScore": null,
        "AwayTeamScore": null
    },
    {
        "MatchNumber": 453,
        "RoundNumber": 5,
        "DateUtc": "2024-05-01 01:40:00Z",
        "Location": "Chase Field",
        "HomeTeam": "Arizona Diamondbacks",
        "AwayTeam": "Los Angeles Dodgers",
        "Group": null,
        "HomeTeamScore": null,
        "AwayTeamScore": null
    },
    {
        "MatchNumber": 471,
        "RoundNumber": 6,
        "DateUtc": "2024-05-02 01:40:00Z",
        "Location": "Chase Field",
        "HomeTeam": "Arizona Diamondbacks",
        "AwayTeam": "Los Angeles Dodgers",
        "Group": null,
        "HomeTeamScore": null,
        "AwayTeamScore": null
    },
    {
        "MatchNumber": 492,
        "RoundNumber": 6,
        "DateUtc": "2024-05-04 02:10:00Z",
        "Location": "Dodger Stadium",
        "HomeTeam": "Los Angeles Dodgers",
        "AwayTeam": "Atlanta Braves",
        "Group": null,
        "HomeTeamScore": null,
        "AwayTeamScore": null
    },
    {
        "MatchNumber": 507,
        "RoundNumber": 6,
        "DateUtc": "2024-05-05 01:10:00Z",
        "Location": "Dodger Stadium",
        "HomeTeam": "Los Angeles Dodgers",
        "AwayTeam": "Atlanta Braves",
        "Group": null,
        "HomeTeamScore": null,
        "AwayTeamScore": null
    },
    {
        "MatchNumber": 521,
        "RoundNumber": 6,
        "DateUtc": "2024-05-05 20:10:00Z",
        "Location": "Dodger Stadium",
        "HomeTeam": "Los Angeles Dodgers",
        "AwayTeam": "Atlanta Braves",
        "Group": null,
        "HomeTeamScore": null,
        "AwayTeamScore": null
    },
    {
        "MatchNumber": 532,
        "RoundNumber": 6,
        "DateUtc": "2024-05-07 02:10:00Z",
        "Location": "Dodger Stadium",
        "HomeTeam": "Los Angeles Dodgers",
        "AwayTeam": "Miami Marlins",
        "Group": null,
        "HomeTeamScore": null,
        "AwayTeamScore": null
    },
    {
        "MatchNumber": 547,
        "RoundNumber": 6,
        "DateUtc": "2024-05-08 02:10:00Z",
        "Location": "Dodger Stadium",
        "HomeTeam": "Los Angeles Dodgers",
        "AwayTeam": "Miami Marlins",
        "Group": null,
        "HomeTeamScore": null,
        "AwayTeamScore": null
    },
    {
        "MatchNumber": 554,
        "RoundNumber": 7,
        "DateUtc": "2024-05-08 19:10:00Z",
        "Location": "Dodger Stadium",
        "HomeTeam": "Los Angeles Dodgers",
        "AwayTeam": "Miami Marlins",
        "Group": null,
        "HomeTeamScore": null,
        "AwayTeamScore": null
    },
    {
        "MatchNumber": 583,
        "RoundNumber": 7,
        "DateUtc": "2024-05-11 01:40:00Z",
        "Location": "Petco Park",
        "HomeTeam": "San Diego Padres",
        "AwayTeam": "Los Angeles Dodgers",
        "Group": null,
        "HomeTeamScore": null,
        "AwayTeamScore": null
    },
    {
        "MatchNumber": 598,
        "RoundNumber": 7,
        "DateUtc": "2024-05-12 00:40:00Z",
        "Location": "Petco Park",
        "HomeTeam": "San Diego Padres",
        "AwayTeam": "Los Angeles Dodgers",
        "Group": null,
        "HomeTeamScore": null,
        "AwayTeamScore": null
    },
    {
        "MatchNumber": 613,
        "RoundNumber": 7,
        "DateUtc": "2024-05-12 20:10:00Z",
        "Location": "Petco Park",
        "HomeTeam": "San Diego Padres",
        "AwayTeam": "Los Angeles Dodgers",
        "Group": null,
        "HomeTeamScore": null,
        "AwayTeamScore": null
    },
    {
        "MatchNumber": 629,
        "RoundNumber": 7,
        "DateUtc": "2024-05-14 01:45:00Z",
        "Location": "Oracle Park",
        "HomeTeam": "San Francisco Giants",
        "AwayTeam": "Los Angeles Dodgers",
        "Group": null,
        "HomeTeamScore": null,
        "AwayTeamScore": null
    },
    {
        "MatchNumber": 644,
        "RoundNumber": 7,
        "DateUtc": "2024-05-15 01:45:00Z",
        "Location": "Oracle Park",
        "HomeTeam": "San Francisco Giants",
        "AwayTeam": "Los Angeles Dodgers",
        "Group": null,
        "HomeTeamScore": null,
        "AwayTeamScore": null
    },
    {
        "MatchNumber": 659,
        "RoundNumber": 8,
        "DateUtc": "2024-05-16 01:45:00Z",
        "Location": "Oracle Park",
        "HomeTeam": "San Francisco Giants",
        "AwayTeam": "Los Angeles Dodgers",
        "Group": null,
        "HomeTeamScore": null,
        "AwayTeamScore": null
    },
    {
        "MatchNumber": 665,
        "RoundNumber": 8,
        "DateUtc": "2024-05-17 02:10:00Z",
        "Location": "Dodger Stadium",
        "HomeTeam": "Los Angeles Dodgers",
        "AwayTeam": "Cincinnati Reds",
        "Group": null,
        "HomeTeamScore": null,
        "AwayTeamScore": null
    },
    {
        "MatchNumber": 679,
        "RoundNumber": 8,
        "DateUtc": "2024-05-18 02:10:00Z",
        "Location": "Dodger Stadium",
        "HomeTeam": "Los Angeles Dodgers",
        "AwayTeam": "Cincinnati Reds",
        "Group": null,
        "HomeTeamScore": null,
        "AwayTeamScore": null
    },
    {
        "MatchNumber": 695,
        "RoundNumber": 8,
        "DateUtc": "2024-05-19 01:10:00Z",
        "Location": "Dodger Stadium",
        "HomeTeam": "Los Angeles Dodgers",
        "AwayTeam": "Cincinnati Reds",
        "Group": null,
        "HomeTeamScore": null,
        "AwayTeamScore": null
    },
    {
        "MatchNumber": 709,
        "RoundNumber": 8,
        "DateUtc": "2024-05-19 20:10:00Z",
        "Location": "Dodger Stadium",
        "HomeTeam": "Los Angeles Dodgers",
        "AwayTeam": "Cincinnati Reds",
        "Group": null,
        "HomeTeamScore": null,
        "AwayTeamScore": null
    },
    {
        "MatchNumber": 721,
        "RoundNumber": 8,
        "DateUtc": "2024-05-21 02:10:00Z",
        "Location": "Dodger Stadium",
        "HomeTeam": "Los Angeles Dodgers",
        "AwayTeam": "Arizona Diamondbacks",
        "Group": null,
        "HomeTeamScore": null,
        "AwayTeamScore": null
    },
    {
        "MatchNumber": 736,
        "RoundNumber": 8,
        "DateUtc": "2024-05-22 02:10:00Z",
        "Location": "Dodger Stadium",
        "HomeTeam": "Los Angeles Dodgers",
        "AwayTeam": "Arizona Diamondbacks",
        "Group": null,
        "HomeTeamScore": null,
        "AwayTeamScore": null
    },
    {
        "MatchNumber": 751,
        "RoundNumber": 9,
        "DateUtc": "2024-05-23 02:10:00Z",
        "Location": "Dodger Stadium",
        "HomeTeam": "Los Angeles Dodgers",
        "AwayTeam": "Arizona Diamondbacks",
        "Group": null,
        "HomeTeamScore": null,
        "AwayTeamScore": null
    },
    {
        "MatchNumber": 764,
        "RoundNumber": 9,
        "DateUtc": "2024-05-24 23:10:00Z",
        "Location": "Great American Ball Park",
        "HomeTeam": "Cincinnati Reds",
        "AwayTeam": "Los Angeles Dodgers",
        "Group": null,
        "HomeTeamScore": null,
        "AwayTeamScore": null
    },
    {
        "MatchNumber": 784,
        "RoundNumber": 9,
        "DateUtc": "2024-05-25 23:15:00Z",
        "Location": "Great American Ball Park",
        "HomeTeam": "Cincinnati Reds",
        "AwayTeam": "Los Angeles Dodgers",
        "Group": null,
        "HomeTeamScore": null,
        "AwayTeamScore": null
    },
    {
        "MatchNumber": 793,
        "RoundNumber": 9,
        "DateUtc": "2024-05-26 17:40:00Z",
        "Location": "Great American Ball Park",
        "HomeTeam": "Cincinnati Reds",
        "AwayTeam": "Los Angeles Dodgers",
        "Group": null,
        "HomeTeamScore": null,
        "AwayTeamScore": null
    },
    {
        "MatchNumber": 809,
        "RoundNumber": 9,
        "DateUtc": "2024-05-27 20:10:00Z",
        "Location": "Citi Field",
        "HomeTeam": "New York Mets",
        "AwayTeam": "Los Angeles Dodgers",
        "Group": null,
        "HomeTeamScore": null,
        "AwayTeamScore": null
    },
    {
        "MatchNumber": 820,
        "RoundNumber": 9,
        "DateUtc": "2024-05-28 23:10:00Z",
        "Location": "Citi Field",
        "HomeTeam": "New York Mets",
        "AwayTeam": "Los Angeles Dodgers",
        "Group": null,
        "HomeTeamScore": null,
        "AwayTeamScore": null
    },
    {
        "MatchNumber": 835,
        "RoundNumber": 10,
        "DateUtc": "2024-05-29 20:10:00Z",
        "Location": "Citi Field",
        "HomeTeam": "New York Mets",
        "AwayTeam": "Los Angeles Dodgers",
        "Group": null,
        "HomeTeamScore": null,
        "AwayTeamScore": null
    },
    {
        "MatchNumber": 866,
        "RoundNumber": 10,
        "DateUtc": "2024-06-01 02:10:00Z",
        "Location": "Dodger Stadium",
        "HomeTeam": "Los Angeles Dodgers",
        "AwayTeam": "Colorado Rockies",
        "Group": null,
        "HomeTeamScore": null,
        "AwayTeamScore": null
    },
    {
        "MatchNumber": 883,
        "RoundNumber": 10,
        "DateUtc": "2024-06-02 02:10:00Z",
        "Location": "Dodger Stadium",
        "HomeTeam": "Los Angeles Dodgers",
        "AwayTeam": "Colorado Rockies",
        "Group": null,
        "HomeTeamScore": null,
        "AwayTeamScore": null
    },
    {
        "MatchNumber": 897,
        "RoundNumber": 10,
        "DateUtc": "2024-06-02 20:10:00Z",
        "Location": "Dodger Stadium",
        "HomeTeam": "Los Angeles Dodgers",
        "AwayTeam": "Colorado Rockies",
        "Group": null,
        "HomeTeamScore": null,
        "AwayTeamScore": null
    },
    {
        "MatchNumber": 908,
        "RoundNumber": 10,
        "DateUtc": "2024-06-04 22:40:00Z",
        "Location": "PNC Park",
        "HomeTeam": "Pittsburgh Pirates",
        "AwayTeam": "Los Angeles Dodgers",
        "Group": null,
        "HomeTeamScore": null,
        "AwayTeamScore": null
    },
    {
        "MatchNumber": 929,
        "RoundNumber": 11,
        "DateUtc": "2024-06-05 22:40:00Z",
        "Location": "PNC Park",
        "HomeTeam": "Pittsburgh Pirates",
        "AwayTeam": "Los Angeles Dodgers",
        "Group": null,
        "HomeTeamScore": null,
        "AwayTeamScore": null
    },
    {
        "MatchNumber": 940,
        "RoundNumber": 11,
        "DateUtc": "2024-06-06 22:40:00Z",
        "Location": "PNC Park",
        "HomeTeam": "Pittsburgh Pirates",
        "AwayTeam": "Los Angeles Dodgers",
        "Group": null,
        "HomeTeamScore": null,
        "AwayTeamScore": null
    },
    {
        "MatchNumber": 951,
        "RoundNumber": 11,
        "DateUtc": "2024-06-07 23:05:00Z",
        "Location": "Yankee Stadium",
        "HomeTeam": "New York Yankees",
        "AwayTeam": "Los Angeles Dodgers",
        "Group": null,
        "HomeTeamScore": null,
        "AwayTeamScore": null
    },
    {
        "MatchNumber": 973,
        "RoundNumber": 11,
        "DateUtc": "2024-06-08 23:35:00Z",
        "Location": "Yankee Stadium",
        "HomeTeam": "New York Yankees",
        "AwayTeam": "Los Angeles Dodgers",
        "Group": null,
        "HomeTeamScore": null,
        "AwayTeamScore": null
    },
    {
        "MatchNumber": 990,
        "RoundNumber": 11,
        "DateUtc": "2024-06-09 23:10:00Z",
        "Location": "Yankee Stadium",
        "HomeTeam": "New York Yankees",
        "AwayTeam": "Los Angeles Dodgers",
        "Group": null,
        "HomeTeamScore": null,
        "AwayTeamScore": null
    },
    {
        "MatchNumber": 1012,
        "RoundNumber": 11,
        "DateUtc": "2024-06-12 02:10:00Z",
        "Location": "Dodger Stadium",
        "HomeTeam": "Los Angeles Dodgers",
        "AwayTeam": "Texas Rangers",
        "Group": null,
        "HomeTeamScore": null,
        "AwayTeamScore": null
    },
    {
        "MatchNumber": 1027,
        "RoundNumber": 12,
        "DateUtc": "2024-06-13 02:10:00Z",
        "Location": "Dodger Stadium",
        "HomeTeam": "Los Angeles Dodgers",
        "AwayTeam": "Texas Rangers",
        "Group": null,
        "HomeTeamScore": null,
        "AwayTeamScore": null
    },
    {
        "MatchNumber": 1038,
        "RoundNumber": 12,
        "DateUtc": "2024-06-14 02:10:00Z",
        "Location": "Dodger Stadium",
        "HomeTeam": "Los Angeles Dodgers",
        "AwayTeam": "Texas Rangers",
        "Group": null,
        "HomeTeamScore": null,
        "AwayTeamScore": null
    },
    {
        "MatchNumber": 1051,
        "RoundNumber": 12,
        "DateUtc": "2024-06-15 02:10:00Z",
        "Location": "Dodger Stadium",
        "HomeTeam": "Los Angeles Dodgers",
        "AwayTeam": "Kansas City Royals",
        "Group": null,
        "HomeTeamScore": null,
        "AwayTeamScore": null
    },
    {
        "MatchNumber": 1066,
        "RoundNumber": 12,
        "DateUtc": "2024-06-16 01:10:00Z",
        "Location": "Dodger Stadium",
        "HomeTeam": "Los Angeles Dodgers",
        "AwayTeam": "Kansas City Royals",
        "Group": null,
        "HomeTeamScore": null,
        "AwayTeamScore": null
    },
    {
        "MatchNumber": 1080,
        "RoundNumber": 12,
        "DateUtc": "2024-06-16 20:10:00Z",
        "Location": "Dodger Stadium",
        "HomeTeam": "Los Angeles Dodgers",
        "AwayTeam": "Kansas City Royals",
        "Group": null,
        "HomeTeamScore": null,
        "AwayTeamScore": null
    },
    {
        "MatchNumber": 1091,
        "RoundNumber": 12,
        "DateUtc": "2024-06-18 00:40:00Z",
        "Location": "Coors Field",
        "HomeTeam": "Colorado Rockies",
        "AwayTeam": "Los Angeles Dodgers",
        "Group": null,
        "HomeTeamScore": null,
        "AwayTeamScore": null
    },
    {
        "MatchNumber": 1105,
        "RoundNumber": 12,
        "DateUtc": "2024-06-19 00:40:00Z",
        "Location": "Coors Field",
        "HomeTeam": "Colorado Rockies",
        "AwayTeam": "Los Angeles Dodgers",
        "Group": null,
        "HomeTeamScore": null,
        "AwayTeamScore": null
    },
    {
        "MatchNumber": 1120,
        "RoundNumber": 13,
        "DateUtc": "2024-06-20 00:40:00Z",
        "Location": "Coors Field",
        "HomeTeam": "Colorado Rockies",
        "AwayTeam": "Los Angeles Dodgers",
        "Group": null,
        "HomeTeamScore": null,
        "AwayTeamScore": null
    },
    {
        "MatchNumber": 1127,
        "RoundNumber": 13,
        "DateUtc": "2024-06-20 19:10:00Z",
        "Location": "Coors Field",
        "HomeTeam": "Colorado Rockies",
        "AwayTeam": "Los Angeles Dodgers",
        "Group": null,
        "HomeTeamScore": null,
        "AwayTeamScore": null
    },
    {
        "MatchNumber": 1145,
        "RoundNumber": 13,
        "DateUtc": "2024-06-22 02:10:00Z",
        "Location": "Dodger Stadium",
        "HomeTeam": "Los Angeles Dodgers",
        "AwayTeam": "Los Angeles Angels",
        "Group": null,
        "HomeTeamScore": null,
        "AwayTeamScore": null
    },
    {
        "MatchNumber": 1160,
        "RoundNumber": 13,
        "DateUtc": "2024-06-23 02:10:00Z",
        "Location": "Dodger Stadium",
        "HomeTeam": "Los Angeles Dodgers",
        "AwayTeam": "Los Angeles Angels",
        "Group": null,
        "HomeTeamScore": null,
        "AwayTeamScore": null
    },
    {
        "MatchNumber": 1181,
        "RoundNumber": 13,
        "DateUtc": "2024-06-25 00:10:00Z",
        "Location": "Guaranteed Rate Field",
        "HomeTeam": "Chicago White Sox",
        "AwayTeam": "Los Angeles Dodgers",
        "Group": null,
        "HomeTeamScore": null,
        "AwayTeamScore": null
    },
    {
        "MatchNumber": 1195,
        "RoundNumber": 13,
        "DateUtc": "2024-06-26 00:10:00Z",
        "Location": "Guaranteed Rate Field",
        "HomeTeam": "Chicago White Sox",
        "AwayTeam": "Los Angeles Dodgers",
        "Group": null,
        "HomeTeamScore": null,
        "AwayTeamScore": null
    },
    {
        "MatchNumber": 1214,
        "RoundNumber": 14,
        "DateUtc": "2024-06-27 00:10:00Z",
        "Location": "Guaranteed Rate Field",
        "HomeTeam": "Chicago White Sox",
        "AwayTeam": "Los Angeles Dodgers",
        "Group": null,
        "HomeTeamScore": null,
        "AwayTeamScore": null
    },
    {
        "MatchNumber": 1239,
        "RoundNumber": 14,
        "DateUtc": "2024-06-29 02:15:00Z",
        "Location": "Oracle Park",
        "HomeTeam": "San Francisco Giants",
        "AwayTeam": "Los Angeles Dodgers",
        "Group": null,
        "HomeTeamScore": null,
        "AwayTeamScore": null
    },
    {
        "MatchNumber": 1251,
        "RoundNumber": 14,
        "DateUtc": "2024-06-29 23:15:00Z",
        "Location": "Oracle Park",
        "HomeTeam": "San Francisco Giants",
        "AwayTeam": "Los Angeles Dodgers",
        "Group": null,
        "HomeTeamScore": null,
        "AwayTeamScore": null
    },
    {
        "MatchNumber": 1266,
        "RoundNumber": 14,
        "DateUtc": "2024-06-30 20:05:00Z",
        "Location": "Oracle Park",
        "HomeTeam": "San Francisco Giants",
        "AwayTeam": "Los Angeles Dodgers",
        "Group": null,
        "HomeTeamScore": null,
        "AwayTeamScore": null
    },
    {
        "MatchNumber": 1287,
        "RoundNumber": 14,
        "DateUtc": "2024-07-03 02:10:00Z",
        "Location": "Dodger Stadium",
        "HomeTeam": "Los Angeles Dodgers",
        "AwayTeam": "Arizona Diamondbacks",
        "Group": null,
        "HomeTeamScore": null,
        "AwayTeamScore": null
    },
    {
        "MatchNumber": 1301,
        "RoundNumber": 15,
        "DateUtc": "2024-07-04 02:10:00Z",
        "Location": "Dodger Stadium",
        "HomeTeam": "Los Angeles Dodgers",
        "AwayTeam": "Arizona Diamondbacks",
        "Group": null,
        "HomeTeamScore": null,
        "AwayTeamScore": null
    },
    {
        "MatchNumber": 1317,
        "RoundNumber": 15,
        "DateUtc": "2024-07-05 01:10:00Z",
        "Location": "Dodger Stadium",
        "HomeTeam": "Los Angeles Dodgers",
        "AwayTeam": "Arizona Diamondbacks",
        "Group": null,
        "HomeTeamScore": null,
        "AwayTeamScore": null
    },
    {
        "MatchNumber": 1332,
        "RoundNumber": 15,
        "DateUtc": "2024-07-06 02:10:00Z",
        "Location": "Dodger Stadium",
        "HomeTeam": "Los Angeles Dodgers",
        "AwayTeam": "Milwaukee Brewers",
        "Group": null,
        "HomeTeamScore": null,
        "AwayTeamScore": null
    },
    {
        "MatchNumber": 1345,
        "RoundNumber": 15,
        "DateUtc": "2024-07-06 23:15:00Z",
        "Location": "Dodger Stadium",
        "HomeTeam": "Los Angeles Dodgers",
        "AwayTeam": "Milwaukee Brewers",
        "Group": null,
        "HomeTeamScore": null,
        "AwayTeamScore": null
    },
    {
        "MatchNumber": 1362,
        "RoundNumber": 15,
        "DateUtc": "2024-07-07 20:10:00Z",
        "Location": "Dodger Stadium",
        "HomeTeam": "Los Angeles Dodgers",
        "AwayTeam": "Milwaukee Brewers",
        "Group": null,
        "HomeTeamScore": null,
        "AwayTeamScore": null
    },
    {
        "MatchNumber": 1372,
        "RoundNumber": 15,
        "DateUtc": "2024-07-09 22:40:00Z",
        "Location": "Citizens Bank Park",
        "HomeTeam": "Philadelphia Phillies",
        "AwayTeam": "Los Angeles Dodgers",
        "Group": null,
        "HomeTeamScore": null,
        "AwayTeamScore": null
    },
    {
        "MatchNumber": 1390,
        "RoundNumber": 16,
        "DateUtc": "2024-07-10 23:05:00Z",
        "Location": "Citizens Bank Park",
        "HomeTeam": "Philadelphia Phillies",
        "AwayTeam": "Los Angeles Dodgers",
        "Group": null,
        "HomeTeamScore": null,
        "AwayTeamScore": null
    },
    {
        "MatchNumber": 1405,
        "RoundNumber": 16,
        "DateUtc": "2024-07-11 22:05:00Z",
        "Location": "Citizens Bank Park",
        "HomeTeam": "Philadelphia Phillies",
        "AwayTeam": "Los Angeles Dodgers",
        "Group": null,
        "HomeTeamScore": null,
        "AwayTeamScore": null
    },
    {
        "MatchNumber": 1412,
        "RoundNumber": 16,
        "DateUtc": "2024-07-12 22:40:00Z",
        "Location": "Comerica Park",
        "HomeTeam": "Detroit Tigers",
        "AwayTeam": "Los Angeles Dodgers",
        "Group": null,
        "HomeTeamScore": null,
        "AwayTeamScore": null
    },
    {
        "MatchNumber": 1427,
        "RoundNumber": 16,
        "DateUtc": "2024-07-13 17:10:00Z",
        "Location": "Comerica Park",
        "HomeTeam": "Detroit Tigers",
        "AwayTeam": "Los Angeles Dodgers",
        "Group": null,
        "HomeTeamScore": null,
        "AwayTeamScore": null
    },
    {
        "MatchNumber": 1445,
        "RoundNumber": 16,
        "DateUtc": "2024-07-14 17:40:00Z",
        "Location": "Comerica Park",
        "HomeTeam": "Detroit Tigers",
        "AwayTeam": "Los Angeles Dodgers",
        "Group": null,
        "HomeTeamScore": null,
        "AwayTeamScore": null
    },
    {
        "MatchNumber": 1469,
        "RoundNumber": 17,
        "DateUtc": "2024-07-20 02:10:00Z",
        "Location": "Dodger Stadium",
        "HomeTeam": "Los Angeles Dodgers",
        "AwayTeam": "Boston Red Sox",
        "Group": null,
        "HomeTeamScore": null,
        "AwayTeamScore": null
    },
    {
        "MatchNumber": 1482,
        "RoundNumber": 17,
        "DateUtc": "2024-07-20 23:15:00Z",
        "Location": "Dodger Stadium",
        "HomeTeam": "Los Angeles Dodgers",
        "AwayTeam": "Boston Red Sox",
        "Group": null,
        "HomeTeamScore": null,
        "AwayTeamScore": null
    },
    {
        "MatchNumber": 1499,
        "RoundNumber": 17,
        "DateUtc": "2024-07-21 20:10:00Z",
        "Location": "Dodger Stadium",
        "HomeTeam": "Los Angeles Dodgers",
        "AwayTeam": "Boston Red Sox",
        "Group": null,
        "HomeTeamScore": null,
        "AwayTeamScore": null
    },
    {
        "MatchNumber": 1513,
        "RoundNumber": 17,
        "DateUtc": "2024-07-23 02:10:00Z",
        "Location": "Dodger Stadium",
        "HomeTeam": "Los Angeles Dodgers",
        "AwayTeam": "San Francisco Giants",
        "Group": null,
        "HomeTeamScore": null,
        "AwayTeamScore": null
    },
    {
        "MatchNumber": 1528,
        "RoundNumber": 17,
        "DateUtc": "2024-07-24 02:10:00Z",
        "Location": "Dodger Stadium",
        "HomeTeam": "Los Angeles Dodgers",
        "AwayTeam": "San Francisco Giants",
        "Group": null,
        "HomeTeamScore": null,
        "AwayTeamScore": null
    },
    {
        "MatchNumber": 1543,
        "RoundNumber": 18,
        "DateUtc": "2024-07-25 02:10:00Z",
        "Location": "Dodger Stadium",
        "HomeTeam": "Los Angeles Dodgers",
        "AwayTeam": "San Francisco Giants",
        "Group": null,
        "HomeTeamScore": null,
        "AwayTeamScore": null
    },
    {
        "MatchNumber": 1549,
        "RoundNumber": 18,
        "DateUtc": "2024-07-25 20:10:00Z",
        "Location": "Dodger Stadium",
        "HomeTeam": "Los Angeles Dodgers",
        "AwayTeam": "San Francisco Giants",
        "Group": null,
        "HomeTeamScore": null,
        "AwayTeamScore": null
    },
    {
        "MatchNumber": 1560,
        "RoundNumber": 18,
        "DateUtc": "2024-07-27 00:10:00Z",
        "Location": "Minute Maid Park",
        "HomeTeam": "Houston Astros",
        "AwayTeam": "Los Angeles Dodgers",
        "Group": null,
        "HomeTeamScore": null,
        "AwayTeamScore": null
    },
    {
        "MatchNumber": 1576,
        "RoundNumber": 18,
        "DateUtc": "2024-07-27 23:10:00Z",
        "Location": "Minute Maid Park",
        "HomeTeam": "Houston Astros",
        "AwayTeam": "Los Angeles Dodgers",
        "Group": null,
        "HomeTeamScore": null,
        "AwayTeamScore": null
    },
    {
        "MatchNumber": 1591,
        "RoundNumber": 18,
        "DateUtc": "2024-07-28 18:10:00Z",
        "Location": "Minute Maid Park",
        "HomeTeam": "Houston Astros",
        "AwayTeam": "Los Angeles Dodgers",
        "Group": null,
        "HomeTeamScore": null,
        "AwayTeamScore": null
    },
    {
        "MatchNumber": 1622,
        "RoundNumber": 18,
        "DateUtc": "2024-07-31 01:40:00Z",
        "Location": "Petco Park",
        "HomeTeam": "San Diego Padres",
        "AwayTeam": "Los Angeles Dodgers",
        "Group": null,
        "HomeTeamScore": null,
        "AwayTeamScore": null
    },
    {
        "MatchNumber": 1635,
        "RoundNumber": 19,
        "DateUtc": "2024-08-01 00:40:00Z",
        "Location": "Petco Park",
        "HomeTeam": "San Diego Padres",
        "AwayTeam": "Los Angeles Dodgers",
        "Group": null,
        "HomeTeamScore": null,
        "AwayTeamScore": null
    },
    {
        "MatchNumber": 1655,
        "RoundNumber": 19,
        "DateUtc": "2024-08-03 01:40:00Z",
        "Location": "Oakland Coliseum",
        "HomeTeam": "Oakland Athletics",
        "AwayTeam": "Los Angeles Dodgers",
        "Group": null,
        "HomeTeamScore": null,
        "AwayTeamScore": null
    },
    {
        "MatchNumber": 1670,
        "RoundNumber": 19,
        "DateUtc": "2024-08-04 01:07:00Z",
        "Location": "Oakland Coliseum",
        "HomeTeam": "Oakland Athletics",
        "AwayTeam": "Los Angeles Dodgers",
        "Group": null,
        "HomeTeamScore": null,
        "AwayTeamScore": null
    },
    {
        "MatchNumber": 1685,
        "RoundNumber": 19,
        "DateUtc": "2024-08-04 20:07:00Z",
        "Location": "Oakland Coliseum",
        "HomeTeam": "Oakland Athletics",
        "AwayTeam": "Los Angeles Dodgers",
        "Group": null,
        "HomeTeamScore": null,
        "AwayTeamScore": null
    },
    {
        "MatchNumber": 1695,
        "RoundNumber": 19,
        "DateUtc": "2024-08-06 02:10:00Z",
        "Location": "Dodger Stadium",
        "HomeTeam": "Los Angeles Dodgers",
        "AwayTeam": "Philadelphia Phillies",
        "Group": null,
        "HomeTeamScore": null,
        "AwayTeamScore": null
    },
    {
        "MatchNumber": 1710,
        "RoundNumber": 19,
        "DateUtc": "2024-08-07 02:10:00Z",
        "Location": "Dodger Stadium",
        "HomeTeam": "Los Angeles Dodgers",
        "AwayTeam": "Philadelphia Phillies",
        "Group": null,
        "HomeTeamScore": null,
        "AwayTeamScore": null
    },
    {
        "MatchNumber": 1725,
        "RoundNumber": 20,
        "DateUtc": "2024-08-08 02:10:00Z",
        "Location": "Dodger Stadium",
        "HomeTeam": "Los Angeles Dodgers",
        "AwayTeam": "Philadelphia Phillies",
        "Group": null,
        "HomeTeamScore": null,
        "AwayTeamScore": null
    },
    {
        "MatchNumber": 1748,
        "RoundNumber": 20,
        "DateUtc": "2024-08-10 02:10:00Z",
        "Location": "Dodger Stadium",
        "HomeTeam": "Los Angeles Dodgers",
        "AwayTeam": "Pittsburgh Pirates",
        "Group": null,
        "HomeTeamScore": null,
        "AwayTeamScore": null
    },
    {
        "MatchNumber": 1764,
        "RoundNumber": 20,
        "DateUtc": "2024-08-11 01:10:00Z",
        "Location": "Dodger Stadium",
        "HomeTeam": "Los Angeles Dodgers",
        "AwayTeam": "Pittsburgh Pirates",
        "Group": null,
        "HomeTeamScore": null,
        "AwayTeamScore": null
    },
    {
        "MatchNumber": 1776,
        "RoundNumber": 20,
        "DateUtc": "2024-08-11 20:10:00Z",
        "Location": "Dodger Stadium",
        "HomeTeam": "Los Angeles Dodgers",
        "AwayTeam": "Pittsburgh Pirates",
        "Group": null,
        "HomeTeamScore": null,
        "AwayTeamScore": null
    },
    {
        "MatchNumber": 1785,
        "RoundNumber": 20,
        "DateUtc": "2024-08-13 00:10:00Z",
        "Location": "American Family Field",
        "HomeTeam": "Milwaukee Brewers",
        "AwayTeam": "Los Angeles Dodgers",
        "Group": null,
        "HomeTeamScore": null,
        "AwayTeamScore": null
    },
    {
        "MatchNumber": 1800,
        "RoundNumber": 20,
        "DateUtc": "2024-08-14 00:10:00Z",
        "Location": "American Family Field",
        "HomeTeam": "Milwaukee Brewers",
        "AwayTeam": "Los Angeles Dodgers",
        "Group": null,
        "HomeTeamScore": null,
        "AwayTeamScore": null
    },
    {
        "MatchNumber": 1817,
        "RoundNumber": 21,
        "DateUtc": "2024-08-15 00:10:00Z",
        "Location": "American Family Field",
        "HomeTeam": "Milwaukee Brewers",
        "AwayTeam": "Los Angeles Dodgers",
        "Group": null,
        "HomeTeamScore": null,
        "AwayTeamScore": null
    },
    {
        "MatchNumber": 1822,
        "RoundNumber": 21,
        "DateUtc": "2024-08-15 18:10:00Z",
        "Location": "American Family Field",
        "HomeTeam": "Milwaukee Brewers",
        "AwayTeam": "Los Angeles Dodgers",
        "Group": null,
        "HomeTeamScore": null,
        "AwayTeamScore": null
    },
    {
        "MatchNumber": 1838,
        "RoundNumber": 21,
        "DateUtc": "2024-08-17 00:15:00Z",
        "Location": "Busch Stadium",
        "HomeTeam": "St. Louis Cardinals",
        "AwayTeam": "Los Angeles Dodgers",
        "Group": null,
        "HomeTeamScore": null,
        "AwayTeamScore": null
    },
    {
        "MatchNumber": 1852,
        "RoundNumber": 21,
        "DateUtc": "2024-08-17 23:15:00Z",
        "Location": "Busch Stadium",
        "HomeTeam": "St. Louis Cardinals",
        "AwayTeam": "Los Angeles Dodgers",
        "Group": null,
        "HomeTeamScore": null,
        "AwayTeamScore": null
    },
    {
        "MatchNumber": 1864,
        "RoundNumber": 21,
        "DateUtc": "2024-08-18 18:15:00Z",
        "Location": "Busch Stadium",
        "HomeTeam": "St. Louis Cardinals",
        "AwayTeam": "Los Angeles Dodgers",
        "Group": null,
        "HomeTeamScore": null,
        "AwayTeamScore": null
    },
    {
        "MatchNumber": 1880,
        "RoundNumber": 21,
        "DateUtc": "2024-08-20 02:10:00Z",
        "Location": "Dodger Stadium",
        "HomeTeam": "Los Angeles Dodgers",
        "AwayTeam": "Seattle Mariners",
        "Group": null,
        "HomeTeamScore": null,
        "AwayTeamScore": null
    },
    {
        "MatchNumber": 1895,
        "RoundNumber": 21,
        "DateUtc": "2024-08-21 02:10:00Z",
        "Location": "Dodger Stadium",
        "HomeTeam": "Los Angeles Dodgers",
        "AwayTeam": "Seattle Mariners",
        "Group": null,
        "HomeTeamScore": null,
        "AwayTeamScore": null
    },
    {
        "MatchNumber": 1910,
        "RoundNumber": 22,
        "DateUtc": "2024-08-22 02:10:00Z",
        "Location": "Dodger Stadium",
        "HomeTeam": "Los Angeles Dodgers",
        "AwayTeam": "Seattle Mariners",
        "Group": null,
        "HomeTeamScore": null,
        "AwayTeamScore": null
    },
    {
        "MatchNumber": 1935,
        "RoundNumber": 22,
        "DateUtc": "2024-08-24 02:10:00Z",
        "Location": "Dodger Stadium",
        "HomeTeam": "Los Angeles Dodgers",
        "AwayTeam": "Tampa Bay Rays",
        "Group": null,
        "HomeTeamScore": null,
        "AwayTeamScore": null
    },
    {
        "MatchNumber": 1950,
        "RoundNumber": 22,
        "DateUtc": "2024-08-25 01:10:00Z",
        "Location": "Dodger Stadium",
        "HomeTeam": "Los Angeles Dodgers",
        "AwayTeam": "Tampa Bay Rays",
        "Group": null,
        "HomeTeamScore": null,
        "AwayTeamScore": null
    },
    {
        "MatchNumber": 1965,
        "RoundNumber": 22,
        "DateUtc": "2024-08-25 20:10:00Z",
        "Location": "Dodger Stadium",
        "HomeTeam": "Los Angeles Dodgers",
        "AwayTeam": "Tampa Bay Rays",
        "Group": null,
        "HomeTeamScore": null,
        "AwayTeamScore": null
    },
    {
        "MatchNumber": 1990,
        "RoundNumber": 22,
        "DateUtc": "2024-08-28 02:10:00Z",
        "Location": "Dodger Stadium",
        "HomeTeam": "Los Angeles Dodgers",
        "AwayTeam": "Baltimore Orioles",
        "Group": null,
        "HomeTeamScore": null,
        "AwayTeamScore": null
    },
    {
        "MatchNumber": 2005,
        "RoundNumber": 23,
        "DateUtc": "2024-08-29 02:10:00Z",
        "Location": "Dodger Stadium",
        "HomeTeam": "Los Angeles Dodgers",
        "AwayTeam": "Baltimore Orioles",
        "Group": null,
        "HomeTeamScore": null,
        "AwayTeamScore": null
    },
    {
        "MatchNumber": 2016,
        "RoundNumber": 23,
        "DateUtc": "2024-08-30 02:10:00Z",
        "Location": "Dodger Stadium",
        "HomeTeam": "Los Angeles Dodgers",
        "AwayTeam": "Baltimore Orioles",
        "Group": null,
        "HomeTeamScore": null,
        "AwayTeamScore": null
    },
    {
        "MatchNumber": 2030,
        "RoundNumber": 23,
        "DateUtc": "2024-08-31 01:40:00Z",
        "Location": "Chase Field",
        "HomeTeam": "Arizona Diamondbacks",
        "AwayTeam": "Los Angeles Dodgers",
        "Group": null,
        "HomeTeamScore": null,
        "AwayTeamScore": null
    },
    {
        "MatchNumber": 2044,
        "RoundNumber": 23,
        "DateUtc": "2024-09-01 00:10:00Z",
        "Location": "Chase Field",
        "HomeTeam": "Arizona Diamondbacks",
        "AwayTeam": "Los Angeles Dodgers",
        "Group": null,
        "HomeTeamScore": null,
        "AwayTeamScore": null
    },
    {
        "MatchNumber": 2060,
        "RoundNumber": 23,
        "DateUtc": "2024-09-01 20:10:00Z",
        "Location": "Chase Field",
        "HomeTeam": "Arizona Diamondbacks",
        "AwayTeam": "Los Angeles Dodgers",
        "Group": null,
        "HomeTeamScore": null,
        "AwayTeamScore": null
    },
    {
        "MatchNumber": 2066,
        "RoundNumber": 23,
        "DateUtc": "2024-09-02 20:10:00Z",
        "Location": "Chase Field",
        "HomeTeam": "Arizona Diamondbacks",
        "AwayTeam": "Los Angeles Dodgers",
        "Group": null,
        "HomeTeamScore": null,
        "AwayTeamScore": null
    },
    {
        "MatchNumber": 2083,
        "RoundNumber": 23,
        "DateUtc": "2024-09-04 01:38:00Z",
        "Location": "Angel Stadium",
        "HomeTeam": "Los Angeles Angels",
        "AwayTeam": "Los Angeles Dodgers",
        "Group": null,
        "HomeTeamScore": null,
        "AwayTeamScore": null
    },
    {
        "MatchNumber": 2097,
        "RoundNumber": 24,
        "DateUtc": "2024-09-05 01:38:00Z",
        "Location": "Angel Stadium",
        "HomeTeam": "Los Angeles Angels",
        "AwayTeam": "Los Angeles Dodgers",
        "Group": null,
        "HomeTeamScore": null,
        "AwayTeamScore": null
    },
    {
        "MatchNumber": 2124,
        "RoundNumber": 24,
        "DateUtc": "2024-09-07 02:10:00Z",
        "Location": "Dodger Stadium",
        "HomeTeam": "Los Angeles Dodgers",
        "AwayTeam": "Cleveland Guardians",
        "Group": null,
        "HomeTeamScore": null,
        "AwayTeamScore": null
    },
    {
        "MatchNumber": 2139,
        "RoundNumber": 24,
        "DateUtc": "2024-09-08 01:10:00Z",
        "Location": "Dodger Stadium",
        "HomeTeam": "Los Angeles Dodgers",
        "AwayTeam": "Cleveland Guardians",
        "Group": null,
        "HomeTeamScore": null,
        "AwayTeamScore": null
    },
    {
        "MatchNumber": 2153,
        "RoundNumber": 24,
        "DateUtc": "2024-09-08 20:10:00Z",
        "Location": "Dodger Stadium",
        "HomeTeam": "Los Angeles Dodgers",
        "AwayTeam": "Cleveland Guardians",
        "Group": null,
        "HomeTeamScore": null,
        "AwayTeamScore": null
    },
    {
        "MatchNumber": 2162,
        "RoundNumber": 24,
        "DateUtc": "2024-09-10 02:10:00Z",
        "Location": "Dodger Stadium",
        "HomeTeam": "Los Angeles Dodgers",
        "AwayTeam": "Chicago Cubs",
        "Group": null,
        "HomeTeamScore": null,
        "AwayTeamScore": null
    },
    {
        "MatchNumber": 2177,
        "RoundNumber": 24,
        "DateUtc": "2024-09-11 02:10:00Z",
        "Location": "Dodger Stadium",
        "HomeTeam": "Los Angeles Dodgers",
        "AwayTeam": "Chicago Cubs",
        "Group": null,
        "HomeTeamScore": null,
        "AwayTeamScore": null
    },
    {
        "MatchNumber": 2192,
        "RoundNumber": 25,
        "DateUtc": "2024-09-12 02:10:00Z",
        "Location": "Dodger Stadium",
        "HomeTeam": "Los Angeles Dodgers",
        "AwayTeam": "Chicago Cubs",
        "Group": null,
        "HomeTeamScore": null,
        "AwayTeamScore": null
    },
    {
        "MatchNumber": 2208,
        "RoundNumber": 25,
        "DateUtc": "2024-09-13 23:20:00Z",
        "Location": "Truist Park",
        "HomeTeam": "Atlanta Braves",
        "AwayTeam": "Los Angeles Dodgers",
        "Group": null,
        "HomeTeamScore": null,
        "AwayTeamScore": null
    },
    {
        "MatchNumber": 2225,
        "RoundNumber": 25,
        "DateUtc": "2024-09-14 23:20:00Z",
        "Location": "Truist Park",
        "HomeTeam": "Atlanta Braves",
        "AwayTeam": "Los Angeles Dodgers",
        "Group": null,
        "HomeTeamScore": null,
        "AwayTeamScore": null
    },
    {
        "MatchNumber": 2233,
        "RoundNumber": 25,
        "DateUtc": "2024-09-15 17:35:00Z",
        "Location": "Truist Park",
        "HomeTeam": "Atlanta Braves",
        "AwayTeam": "Los Angeles Dodgers",
        "Group": null,
        "HomeTeamScore": null,
        "AwayTeamScore": null
    },
    {
        "MatchNumber": 2248,
        "RoundNumber": 25,
        "DateUtc": "2024-09-16 23:20:00Z",
        "Location": "Truist Park",
        "HomeTeam": "Atlanta Braves",
        "AwayTeam": "Los Angeles Dodgers",
        "Group": null,
        "HomeTeamScore": null,
        "AwayTeamScore": null
    },
    {
        "MatchNumber": 2259,
        "RoundNumber": 25,
        "DateUtc": "2024-09-17 22:40:00Z",
        "Location": "loanDepot park",
        "HomeTeam": "Miami Marlins",
        "AwayTeam": "Los Angeles Dodgers",
        "Group": null,
        "HomeTeamScore": null,
        "AwayTeamScore": null
    },
    {
        "MatchNumber": 2278,
        "RoundNumber": 26,
        "DateUtc": "2024-09-18 22:40:00Z",
        "Location": "loanDepot park",
        "HomeTeam": "Miami Marlins",
        "AwayTeam": "Los Angeles Dodgers",
        "Group": null,
        "HomeTeamScore": null,
        "AwayTeamScore": null
    },
    {
        "MatchNumber": 2291,
        "RoundNumber": 26,
        "DateUtc": "2024-09-19 20:40:00Z",
        "Location": "loanDepot park",
        "HomeTeam": "Miami Marlins",
        "AwayTeam": "Los Angeles Dodgers",
        "Group": null,
        "HomeTeamScore": null,
        "AwayTeamScore": null
    },
    {
        "MatchNumber": 2312,
        "RoundNumber": 26,
        "DateUtc": "2024-09-21 02:10:00Z",
        "Location": "Dodger Stadium",
        "HomeTeam": "Los Angeles Dodgers",
        "AwayTeam": "Colorado Rockies",
        "Group": null,
        "HomeTeamScore": null,
        "AwayTeamScore": null
    },
    {
        "MatchNumber": 2327,
        "RoundNumber": 26,
        "DateUtc": "2024-09-22 01:10:00Z",
        "Location": "Dodger Stadium",
        "HomeTeam": "Los Angeles Dodgers",
        "AwayTeam": "Colorado Rockies",
        "Group": null,
        "HomeTeamScore": null,
        "AwayTeamScore": null
    },
    {
        "MatchNumber": 2341,
        "RoundNumber": 26,
        "DateUtc": "2024-09-22 20:10:00Z",
        "Location": "Dodger Stadium",
        "HomeTeam": "Los Angeles Dodgers",
        "AwayTeam": "Colorado Rockies",
        "Group": null,
        "HomeTeamScore": null,
        "AwayTeamScore": null
    },
    {
        "MatchNumber": 2361,
        "RoundNumber": 26,
        "DateUtc": "2024-09-25 02:10:00Z",
        "Location": "Dodger Stadium",
        "HomeTeam": "Los Angeles Dodgers",
        "AwayTeam": "San Diego Padres",
        "Group": null,
        "HomeTeamScore": null,
        "AwayTeamScore": null
    },
    {
        "MatchNumber": 2376,
        "RoundNumber": 27,
        "DateUtc": "2024-09-26 02:10:00Z",
        "Location": "Dodger Stadium",
        "HomeTeam": "Los Angeles Dodgers",
        "AwayTeam": "San Diego Padres",
        "Group": null,
        "HomeTeamScore": null,
        "AwayTeamScore": null
    },
    {
        "MatchNumber": 2385,
        "RoundNumber": 27,
        "DateUtc": "2024-09-27 02:10:00Z",
        "Location": "Dodger Stadium",
        "HomeTeam": "Los Angeles Dodgers",
        "AwayTeam": "San Diego Padres",
        "Group": null,
        "HomeTeamScore": null,
        "AwayTeamScore": null
    },
    {
        "MatchNumber": 2394,
        "RoundNumber": 27,
        "DateUtc": "2024-09-28 00:10:00Z",
        "Location": "Coors Field",
        "HomeTeam": "Colorado Rockies",
        "AwayTeam": "Los Angeles Dodgers",
        "Group": null,
        "HomeTeamScore": null,
        "AwayTeamScore": null
    },
    {
        "MatchNumber": 2412,
        "RoundNumber": 27,
        "DateUtc": "2024-09-29 00:10:00Z",
        "Location": "Coors Field",
        "HomeTeam": "Colorado Rockies",
        "AwayTeam": "Los Angeles Dodgers",
        "Group": null,
        "HomeTeamScore": null,
        "AwayTeamScore": null
    },
    {
        "MatchNumber": 2423,
        "RoundNumber": 27,
        "DateUtc": "2024-09-29 19:10:00Z",
        "Location": "Coors Field",
        "HomeTeam": "Colorado Rockies",
        "AwayTeam": "Los Angeles Dodgers",
        "Group": null,
        "HomeTeamScore": null,
        "AwayTeamScore": null
    }
]